{"商品分析-trend": {"30d": [{"d": "05/25", "dt": "2026/05/25", "GoodsCount": 239582, "LiveGoodsCount": 219166, "AwemeGoodsCount": 14392, "AvgGuestPrice": 38.637157}, {"d": "05/26", "dt": "2026/05/26", "GoodsCount": 248825, "LiveGoodsCount": 229264, "AwemeGoodsCount": 14344, "AvgGuestPrice": 39.678833}, {"d": "05/27", "dt": "2026/05/27", "GoodsCount": 248816, "LiveGoodsCount": 228697, "AwemeGoodsCount": 14138, "AvgGuestPrice": 42.067871}, {"d": "05/28", "dt": "2026/05/28", "GoodsCount": 253202, "LiveGoodsCount": 233362, "AwemeGoodsCount": 14100, "AvgGuestPrice": 43.885674}, {"d": "05/29", "dt": "2026/05/29", "GoodsCount": 250295, "LiveGoodsCount": 231290, "AwemeGoodsCount": 14541, "AvgGuestPrice": 42.61829}, {"d": "05/30", "dt": "2026/05/30", "GoodsCount": 244810, "LiveGoodsCount": 225932, "AwemeGoodsCount": 14047, "AvgGuestPrice": 42.987202}, {"d": "05/31", "dt": "2026/05/31", "GoodsCount": 231384, "LiveGoodsCount": 212574, "AwemeGoodsCount": 13771, "AvgGuestPrice": 52.343895}, {"d": "06/01", "dt": "2026/06/01", "GoodsCount": 222739, "LiveGoodsCount": 203248, "AwemeGoodsCount": 14322, "AvgGuestPrice": 53.266994}, {"d": "06/02", "dt": "2026/06/02", "GoodsCount": 243754, "LiveGoodsCount": 226054, "AwemeGoodsCount": 14698, "AvgGuestPrice": 44.677917}, {"d": "06/03", "dt": "2026/06/03", "GoodsCount": 250280, "LiveGoodsCount": 232771, "AwemeGoodsCount": 14887, "AvgGuestPrice": 50.675816}, {"d": "06/04", "dt": "2026/06/04", "GoodsCount": 249316, "LiveGoodsCount": 231581, "AwemeGoodsCount": 14979, "AvgGuestPrice": 47.095802}, {"d": "06/05", "dt": "2026/06/05", "GoodsCount": 249388, "LiveGoodsCount": 230998, "AwemeGoodsCount": 14842, "AvgGuestPrice": 50.340282}, {"d": "06/06", "dt": "2026/06/06", "GoodsCount": 242004, "LiveGoodsCount": 222749, "AwemeGoodsCount": 14682, "AvgGuestPrice": 57.382809}, {"d": "06/07", "dt": "2026/06/07", "GoodsCount": 233523, "LiveGoodsCount": 214771, "AwemeGoodsCount": 14362, "AvgGuestPrice": 55.947479}, {"d": "06/08", "dt": "2026/06/08", "GoodsCount": 230852, "LiveGoodsCount": 213169, "AwemeGoodsCount": 14780, "AvgGuestPrice": 48.048431}, {"d": "06/09", "dt": "2026/06/09", "GoodsCount": 243531, "LiveGoodsCount": 225773, "AwemeGoodsCount": 14991, "AvgGuestPrice": 45.494358}, {"d": "06/10", "dt": "2026/06/10", "GoodsCount": 246527, "LiveGoodsCount": 228520, "AwemeGoodsCount": 15244, "AvgGuestPrice": 37.832123}, {"d": "06/11", "dt": "2026/06/11", "GoodsCount": 252266, "LiveGoodsCount": 233087, "AwemeGoodsCount": 15355, "AvgGuestPrice": 41.219879}, {"d": "06/12", "dt": "2026/06/12", "GoodsCount": 254223, "LiveGoodsCount": 235661, "AwemeGoodsCount": 14450, "AvgGuestPrice": 41.751255}, {"d": "06/13", "dt": "2026/06/13", "GoodsCount": 245894, "LiveGoodsCount": 226668, "AwemeGoodsCount": 14947, "AvgGuestPrice": 43.197189}, {"d": "06/14", "dt": "2026/06/14", "GoodsCount": 236778, "LiveGoodsCount": 217509, "AwemeGoodsCount": 14228, "AvgGuestPrice": 49.783421}, {"d": "06/15", "dt": "2026/06/15", "GoodsCount": 238331, "LiveGoodsCount": 219466, "AwemeGoodsCount": 15039, "AvgGuestPrice": 41.141663}, {"d": "06/16", "dt": "2026/06/16", "GoodsCount": 253216, "LiveGoodsCount": 234420, "AwemeGoodsCount": 14884, "AvgGuestPrice": 42.885818}, {"d": "06/17", "dt": "2026/06/17", "GoodsCount": 252662, "LiveGoodsCount": 234228, "AwemeGoodsCount": 14758, "AvgGuestPrice": 45.463711}, {"d": "06/18", "dt": "2026/06/18", "GoodsCount": 247539, "LiveGoodsCount": 229592, "AwemeGoodsCount": 14370, "AvgGuestPrice": 46.03257}, {"d": "06/19", "dt": "2026/06/19", "GoodsCount": 211019, "LiveGoodsCount": 194410, "AwemeGoodsCount": 13758, "AvgGuestPrice": 38.69376}, {"d": "06/20", "dt": "2026/06/20", "GoodsCount": 226069, "LiveGoodsCount": 211438, "AwemeGoodsCount": 13488, "AvgGuestPrice": 38.576168}, {"d": "06/21", "dt": "2026/06/21", "GoodsCount": 236817, "LiveGoodsCount": 222336, "AwemeGoodsCount": 14047, "AvgGuestPrice": 37.16301}, {"d": "06/22", "dt": "2026/06/22", "GoodsCount": 241560, "LiveGoodsCount": 229129, "AwemeGoodsCount": 13626, "AvgGuestPrice": 35.084633}, {"d": "06/23", "dt": "2026/06/23", "GoodsCount": 242899, "LiveGoodsCount": 237191, "AwemeGoodsCount": 9074, "AvgGuestPrice": 45.358601}], "90d": [{"d": "03/26", "dt": "2026/03/26", "GoodsCount": 207984, "LiveGoodsCount": 189584, "AwemeGoodsCount": 13516, "AvgGuestPrice": 37.812206}, {"d": "03/27", "dt": "2026/03/27", "GoodsCount": 207055, "LiveGoodsCount": 188659, "AwemeGoodsCount": 13439, "AvgGuestPrice": 39.459568}, {"d": "03/28", "dt": "2026/03/28", "GoodsCount": 199333, "LiveGoodsCount": 181146, "AwemeGoodsCount": 12718, "AvgGuestPrice": 40.152107}, {"d": "03/29", "dt": "2026/03/29", "GoodsCount": 197577, "LiveGoodsCount": 179315, "AwemeGoodsCount": 12679, "AvgGuestPrice": 41.375027}, {"d": "03/30", "dt": "2026/03/30", "GoodsCount": 201591, "LiveGoodsCount": 182713, "AwemeGoodsCount": 13377, "AvgGuestPrice": 37.776035}, {"d": "03/31", "dt": "2026/03/31", "GoodsCount": 206096, "LiveGoodsCount": 187440, "AwemeGoodsCount": 13331, "AvgGuestPrice": 35.800137}, {"d": "04/01", "dt": "2026/04/01", "GoodsCount": 206169, "LiveGoodsCount": 187721, "AwemeGoodsCount": 13188, "AvgGuestPrice": 38.969082}, {"d": "04/02", "dt": "2026/04/02", "GoodsCount": 210194, "LiveGoodsCount": 191669, "AwemeGoodsCount": 13373, "AvgGuestPrice": 40.519215}, {"d": "04/03", "dt": "2026/04/03", "GoodsCount": 208135, "LiveGoodsCount": 189688, "AwemeGoodsCount": 13038, "AvgGuestPrice": 39.178047}, {"d": "04/04", "dt": "2026/04/04", "GoodsCount": 191834, "LiveGoodsCount": 173658, "AwemeGoodsCount": 11749, "AvgGuestPrice": 38.439594}, {"d": "04/05", "dt": "2026/04/05", "GoodsCount": 173496, "LiveGoodsCount": 155011, "AwemeGoodsCount": 11939, "AvgGuestPrice": 35.906456}, {"d": "04/06", "dt": "2026/04/06", "GoodsCount": 193580, "LiveGoodsCount": 175652, "AwemeGoodsCount": 12383, "AvgGuestPrice": 36.85849}, {"d": "04/07", "dt": "2026/04/07", "GoodsCount": 210128, "LiveGoodsCount": 192468, "AwemeGoodsCount": 11679, "AvgGuestPrice": 39.512218}, {"d": "04/08", "dt": "2026/04/08", "GoodsCount": 223132, "LiveGoodsCount": 205054, "AwemeGoodsCount": 13160, "AvgGuestPrice": 38.634308}, {"d": "04/09", "dt": "2026/04/09", "GoodsCount": 226883, "LiveGoodsCount": 208555, "AwemeGoodsCount": 13100, "AvgGuestPrice": 41.702011}, {"d": "04/10", "dt": "2026/04/10", "GoodsCount": 226154, "LiveGoodsCount": 207252, "AwemeGoodsCount": 13327, "AvgGuestPrice": 39.482025}, {"d": "04/11", "dt": "2026/04/11", "GoodsCount": 216206, "LiveGoodsCount": 196791, "AwemeGoodsCount": 13125, "AvgGuestPrice": 41.934963}, {"d": "04/12", "dt": "2026/04/12", "GoodsCount": 210775, "LiveGoodsCount": 190741, "AwemeGoodsCount": 13060, "AvgGuestPrice": 38.120281}, {"d": "04/13", "dt": "2026/04/13", "GoodsCount": 213932, "LiveGoodsCount": 194034, "AwemeGoodsCount": 13369, "AvgGuestPrice": 38.561977}, {"d": "04/14", "dt": "2026/04/14", "GoodsCount": 225616, "LiveGoodsCount": 206011, "AwemeGoodsCount": 13625, "AvgGuestPrice": 40.479313}, {"d": "04/15", "dt": "2026/04/15", "GoodsCount": 223445, "LiveGoodsCount": 203674, "AwemeGoodsCount": 13593, "AvgGuestPrice": 40.495472}, {"d": "04/16", "dt": "2026/04/16", "GoodsCount": 226348, "LiveGoodsCount": 206906, "AwemeGoodsCount": 13893, "AvgGuestPrice": 42.762589}, {"d": "04/17", "dt": "2026/04/17", "GoodsCount": 227619, "LiveGoodsCount": 207955, "AwemeGoodsCount": 13619, "AvgGuestPrice": 41.180191}, {"d": "04/18", "dt": "2026/04/18", "GoodsCount": 223503, "LiveGoodsCount": 203571, "AwemeGoodsCount": 13485, "AvgGuestPrice": 42.879585}, {"d": "04/19", "dt": "2026/04/19", "GoodsCount": 214777, "LiveGoodsCount": 194710, "AwemeGoodsCount": 12701, "AvgGuestPrice": 44.883835}, {"d": "04/20", "dt": "2026/04/20", "GoodsCount": 218273, "LiveGoodsCount": 198616, "AwemeGoodsCount": 13967, "AvgGuestPrice": 40.598457}, {"d": "04/21", "dt": "2026/04/21", "GoodsCount": 230691, "LiveGoodsCount": 211434, "AwemeGoodsCount": 13929, "AvgGuestPrice": 43.936382}, {"d": "04/22", "dt": "2026/04/22", "GoodsCount": 234226, "LiveGoodsCount": 214307, "AwemeGoodsCount": 14151, "AvgGuestPrice": 42.351215}, {"d": "04/23", "dt": "2026/04/23", "GoodsCount": 234906, "LiveGoodsCount": 214985, "AwemeGoodsCount": 13986, "AvgGuestPrice": 41.009373}, {"d": "04/24", "dt": "2026/04/24", "GoodsCount": 235905, "LiveGoodsCount": 216222, "AwemeGoodsCount": 13545, "AvgGuestPrice": 40.191376}, {"d": "04/25", "dt": "2026/04/25", "GoodsCount": 228224, "LiveGoodsCount": 209336, "AwemeGoodsCount": 13777, "AvgGuestPrice": 39.312904}, {"d": "04/26", "dt": "2026/04/26", "GoodsCount": 224956, "LiveGoodsCount": 205328, "AwemeGoodsCount": 13369, "AvgGuestPrice": 43.708374}, {"d": "04/27", "dt": "2026/04/27", "GoodsCount": 229490, "LiveGoodsCount": 209867, "AwemeGoodsCount": 13752, "AvgGuestPrice": 38.549099}, {"d": "04/28", "dt": "2026/04/28", "GoodsCount": 237471, "LiveGoodsCount": 218745, "AwemeGoodsCount": 14240, "AvgGuestPrice": 41.071987}, {"d": "04/29", "dt": "2026/04/29", "GoodsCount": 241130, "LiveGoodsCount": 222523, "AwemeGoodsCount": 13994, "AvgGuestPrice": 40.359119}, {"d": "04/30", "dt": "2026/04/30", "GoodsCount": 233574, "LiveGoodsCount": 215178, "AwemeGoodsCount": 13431, "AvgGuestPrice": 39.167122}, {"d": "05/01", "dt": "2026/05/01", "GoodsCount": 200323, "LiveGoodsCount": 181735, "AwemeGoodsCount": 12787, "AvgGuestPrice": 39.399891}, {"d": "05/02", "dt": "2026/05/02", "GoodsCount": 201591, "LiveGoodsCount": 183341, "AwemeGoodsCount": 12911, "AvgGuestPrice": 40.862015}, {"d": "05/03", "dt": "2026/05/03", "GoodsCount": 206676, "LiveGoodsCount": 188568, "AwemeGoodsCount": 13059, "AvgGuestPrice": 43.004517}, {"d": "05/04", "dt": "2026/05/04", "GoodsCount": 213467, "LiveGoodsCount": 195276, "AwemeGoodsCount": 13134, "AvgGuestPrice": 39.6045}, {"d": "05/05", "dt": "2026/05/05", "GoodsCount": 224903, "LiveGoodsCount": 206849, "AwemeGoodsCount": 13528, "AvgGuestPrice": 42.01112}, {"d": "05/06", "dt": "2026/05/06", "GoodsCount": 232504, "LiveGoodsCount": 214409, "AwemeGoodsCount": 13729, "AvgGuestPrice": 42.587719}, {"d": "05/07", "dt": "2026/05/07", "GoodsCount": 241486, "LiveGoodsCount": 222827, "AwemeGoodsCount": 13992, "AvgGuestPrice": 41.700523}, {"d": "05/08", "dt": "2026/05/08", "GoodsCount": 246260, "LiveGoodsCount": 227873, "AwemeGoodsCount": 13912, "AvgGuestPrice": 41.990814}, {"d": "05/09", "dt": "2026/05/09", "GoodsCount": 242752, "LiveGoodsCount": 223823, "AwemeGoodsCount": 13990, "AvgGuestPrice": 41.256252}, {"d": "05/10", "dt": "2026/05/10", "GoodsCount": 228682, "LiveGoodsCount": 209885, "AwemeGoodsCount": 13448, "AvgGuestPrice": 40.301868}, {"d": "05/11", "dt": "2026/05/11", "GoodsCount": 231156, "LiveGoodsCount": 212038, "AwemeGoodsCount": 14120, "AvgGuestPrice": 41.057713}, {"d": "05/12", "dt": "2026/05/12", "GoodsCount": 238532, "LiveGoodsCount": 219686, "AwemeGoodsCount": 14220, "AvgGuestPrice": 40.838467}, {"d": "05/13", "dt": "2026/05/13", "GoodsCount": 241549, "LiveGoodsCount": 222583, "AwemeGoodsCount": 14183, "AvgGuestPrice": 40.512203}, {"d": "05/14", "dt": "2026/05/14", "GoodsCount": 245570, "LiveGoodsCount": 226298, "AwemeGoodsCount": 14395, "AvgGuestPrice": 40.117733}, {"d": "05/15", "dt": "2026/05/15", "GoodsCount": 245526, "LiveGoodsCount": 224755, "AwemeGoodsCount": 14143, "AvgGuestPrice": 47.011593}, {"d": "05/16", "dt": "2026/05/16", "GoodsCount": 237553, "LiveGoodsCount": 217182, "AwemeGoodsCount": 14017, "AvgGuestPrice": 45.501949}, {"d": "05/17", "dt": "2026/05/17", "GoodsCount": 229828, "LiveGoodsCount": 208916, "AwemeGoodsCount": 14152, "AvgGuestPrice": 46.041325}, {"d": "05/18", "dt": "2026/05/18", "GoodsCount": 228057, "LiveGoodsCount": 207851, "AwemeGoodsCount": 14531, "AvgGuestPrice": 43.228123}, {"d": "05/19", "dt": "2026/05/19", "GoodsCount": 249644, "LiveGoodsCount": 229658, "AwemeGoodsCount": 14569, "AvgGuestPrice": 45.319038}, {"d": "05/20", "dt": "2026/05/20", "GoodsCount": 252176, "LiveGoodsCount": 231314, "AwemeGoodsCount": 14587, "AvgGuestPrice": 45.442436}, {"d": "05/21", "dt": "2026/05/21", "GoodsCount": 249031, "LiveGoodsCount": 229366, "AwemeGoodsCount": 14730, "AvgGuestPrice": 40.365639}, {"d": "05/22", "dt": "2026/05/22", "GoodsCount": 254134, "LiveGoodsCount": 234826, "AwemeGoodsCount": 14745, "AvgGuestPrice": 38.538513}, {"d": "05/23", "dt": "2026/05/23", "GoodsCount": 249447, "LiveGoodsCount": 228966, "AwemeGoodsCount": 14382, "AvgGuestPrice": 39.827339}, {"d": "05/24", "dt": "2026/05/24", "GoodsCount": 236405, "LiveGoodsCount": 215933, "AwemeGoodsCount": 13775, "AvgGuestPrice": 39.004608}, {"d": "05/25", "dt": "2026/05/25", "GoodsCount": 239582, "LiveGoodsCount": 219166, "AwemeGoodsCount": 14392, "AvgGuestPrice": 38.637157}, {"d": "05/26", "dt": "2026/05/26", "GoodsCount": 248825, "LiveGoodsCount": 229264, "AwemeGoodsCount": 14344, "AvgGuestPrice": 39.678833}, {"d": "05/27", "dt": "2026/05/27", "GoodsCount": 248816, "LiveGoodsCount": 228697, "AwemeGoodsCount": 14138, "AvgGuestPrice": 42.067871}, {"d": "05/28", "dt": "2026/05/28", "GoodsCount": 253202, "LiveGoodsCount": 233362, "AwemeGoodsCount": 14100, "AvgGuestPrice": 43.885674}, {"d": "05/29", "dt": "2026/05/29", "GoodsCount": 250295, "LiveGoodsCount": 231290, "AwemeGoodsCount": 14541, "AvgGuestPrice": 42.61829}, {"d": "05/30", "dt": "2026/05/30", "GoodsCount": 244810, "LiveGoodsCount": 225932, "AwemeGoodsCount": 14047, "AvgGuestPrice": 42.987202}, {"d": "05/31", "dt": "2026/05/31", "GoodsCount": 231384, "LiveGoodsCount": 212574, "AwemeGoodsCount": 13771, "AvgGuestPrice": 52.343895}, {"d": "06/01", "dt": "2026/06/01", "GoodsCount": 222739, "LiveGoodsCount": 203248, "AwemeGoodsCount": 14322, "AvgGuestPrice": 53.266994}, {"d": "06/02", "dt": "2026/06/02", "GoodsCount": 243754, "LiveGoodsCount": 226054, "AwemeGoodsCount": 14698, "AvgGuestPrice": 44.677917}, {"d": "06/03", "dt": "2026/06/03", "GoodsCount": 250280, "LiveGoodsCount": 232771, "AwemeGoodsCount": 14887, "AvgGuestPrice": 50.675816}, {"d": "06/04", "dt": "2026/06/04", "GoodsCount": 249316, "LiveGoodsCount": 231581, "AwemeGoodsCount": 14979, "AvgGuestPrice": 47.095802}, {"d": "06/05", "dt": "2026/06/05", "GoodsCount": 249388, "LiveGoodsCount": 230998, "AwemeGoodsCount": 14842, "AvgGuestPrice": 50.340282}, {"d": "06/06", "dt": "2026/06/06", "GoodsCount": 242004, "LiveGoodsCount": 222749, "AwemeGoodsCount": 14682, "AvgGuestPrice": 57.382809}, {"d": "06/07", "dt": "2026/06/07", "GoodsCount": 233523, "LiveGoodsCount": 214771, "AwemeGoodsCount": 14362, "AvgGuestPrice": 55.947479}, {"d": "06/08", "dt": "2026/06/08", "GoodsCount": 230852, "LiveGoodsCount": 213169, "AwemeGoodsCount": 14780, "AvgGuestPrice": 48.048431}, {"d": "06/09", "dt": "2026/06/09", "GoodsCount": 243531, "LiveGoodsCount": 225773, "AwemeGoodsCount": 14991, "AvgGuestPrice": 45.494358}, {"d": "06/10", "dt": "2026/06/10", "GoodsCount": 246527, "LiveGoodsCount": 228520, "AwemeGoodsCount": 15244, "AvgGuestPrice": 37.832123}, {"d": "06/11", "dt": "2026/06/11", "GoodsCount": 252266, "LiveGoodsCount": 233087, "AwemeGoodsCount": 15355, "AvgGuestPrice": 41.219879}, {"d": "06/12", "dt": "2026/06/12", "GoodsCount": 254223, "LiveGoodsCount": 235661, "AwemeGoodsCount": 14450, "AvgGuestPrice": 41.751255}, {"d": "06/13", "dt": "2026/06/13", "GoodsCount": 245894, "LiveGoodsCount": 226668, "AwemeGoodsCount": 14947, "AvgGuestPrice": 43.197189}, {"d": "06/14", "dt": "2026/06/14", "GoodsCount": 236778, "LiveGoodsCount": 217509, "AwemeGoodsCount": 14228, "AvgGuestPrice": 49.783421}, {"d": "06/15", "dt": "2026/06/15", "GoodsCount": 238331, "LiveGoodsCount": 219466, "AwemeGoodsCount": 15039, "AvgGuestPrice": 41.141663}, {"d": "06/16", "dt": "2026/06/16", "GoodsCount": 253216, "LiveGoodsCount": 234420, "AwemeGoodsCount": 14884, "AvgGuestPrice": 42.885818}, {"d": "06/17", "dt": "2026/06/17", "GoodsCount": 252662, "LiveGoodsCount": 234228, "AwemeGoodsCount": 14758, "AvgGuestPrice": 45.463711}, {"d": "06/18", "dt": "2026/06/18", "GoodsCount": 247539, "LiveGoodsCount": 229592, "AwemeGoodsCount": 14370, "AvgGuestPrice": 46.03257}, {"d": "06/19", "dt": "2026/06/19", "GoodsCount": 211019, "LiveGoodsCount": 194410, "AwemeGoodsCount": 13758, "AvgGuestPrice": 38.69376}, {"d": "06/20", "dt": "2026/06/20", "GoodsCount": 226069, "LiveGoodsCount": 211438, "AwemeGoodsCount": 13488, "AvgGuestPrice": 38.576168}, {"d": "06/21", "dt": "2026/06/21", "GoodsCount": 236817, "LiveGoodsCount": 222336, "AwemeGoodsCount": 14047, "AvgGuestPrice": 37.16301}, {"d": "06/22", "dt": "2026/06/22", "GoodsCount": 241560, "LiveGoodsCount": 229129, "AwemeGoodsCount": 13626, "AvgGuestPrice": 35.084633}, {"d": "06/23", "dt": "2026/06/23", "GoodsCount": 242899, "LiveGoodsCount": 237191, "AwemeGoodsCount": 9074, "AvgGuestPrice": 45.358601}]}, "视频分析-trends": {"30d": [{"d": "05/25", "dt": "2026/05/25", "AwemeGoodsCount": 14392, "AwemeSalesGmv": 12122516.7, "AwemeSalesCount": 629305, "AwemeCount": 49602, "AwemeBloggerCount": 15580}, {"d": "05/26", "dt": "2026/05/26", "AwemeGoodsCount": 14344, "AwemeSalesGmv": 14760977.88, "AwemeSalesCount": 785814, "AwemeCount": 50418, "AwemeBloggerCount": 15395}, {"d": "05/27", "dt": "2026/05/27", "AwemeGoodsCount": 14138, "AwemeSalesGmv": 11689323.46, "AwemeSalesCount": 570215, "AwemeCount": 48943, "AwemeBloggerCount": 15664}, {"d": "05/28", "dt": "2026/05/28", "AwemeGoodsCount": 14100, "AwemeSalesGmv": 11488653.04, "AwemeSalesCount": 562557, "AwemeCount": 47646, "AwemeBloggerCount": 15204}, {"d": "05/29", "dt": "2026/05/29", "AwemeGoodsCount": 14541, "AwemeSalesGmv": 13076147.88, "AwemeSalesCount": 678745, "AwemeCount": 50109, "AwemeBloggerCount": 15706}, {"d": "05/30", "dt": "2026/05/30", "AwemeGoodsCount": 14047, "AwemeSalesGmv": 13741023.71, "AwemeSalesCount": 658173, "AwemeCount": 48294, "AwemeBloggerCount": 15375}, {"d": "05/31", "dt": "2026/05/31", "AwemeGoodsCount": 13771, "AwemeSalesGmv": 12882437.21, "AwemeSalesCount": 612166, "AwemeCount": 47001, "AwemeBloggerCount": 15032}, {"d": "06/01", "dt": "2026/06/01", "AwemeGoodsCount": 14322, "AwemeSalesGmv": 12839070.13, "AwemeSalesCount": 633922, "AwemeCount": 49834, "AwemeBloggerCount": 15916}, {"d": "06/02", "dt": "2026/06/02", "AwemeGoodsCount": 14698, "AwemeSalesGmv": 14267777.11, "AwemeSalesCount": 610697, "AwemeCount": 50878, "AwemeBloggerCount": 16231}, {"d": "06/03", "dt": "2026/06/03", "AwemeGoodsCount": 14887, "AwemeSalesGmv": 13680347.07, "AwemeSalesCount": 628174, "AwemeCount": 51656, "AwemeBloggerCount": 16530}, {"d": "06/04", "dt": "2026/06/04", "AwemeGoodsCount": 14979, "AwemeSalesGmv": 13438610.97, "AwemeSalesCount": 668321, "AwemeCount": 51449, "AwemeBloggerCount": 16618}, {"d": "06/05", "dt": "2026/06/05", "AwemeGoodsCount": 14842, "AwemeSalesGmv": 14970736.34, "AwemeSalesCount": 806546, "AwemeCount": 53127, "AwemeBloggerCount": 16911}, {"d": "06/06", "dt": "2026/06/06", "AwemeGoodsCount": 14682, "AwemeSalesGmv": 15324780.42, "AwemeSalesCount": 712453, "AwemeCount": 52340, "AwemeBloggerCount": 16931}, {"d": "06/07", "dt": "2026/06/07", "AwemeGoodsCount": 14362, "AwemeSalesGmv": 14104597.36, "AwemeSalesCount": 602464, "AwemeCount": 49612, "AwemeBloggerCount": 16177}, {"d": "06/08", "dt": "2026/06/08", "AwemeGoodsCount": 14780, "AwemeSalesGmv": 12747114.89, "AwemeSalesCount": 576907, "AwemeCount": 51162, "AwemeBloggerCount": 17280}, {"d": "06/09", "dt": "2026/06/09", "AwemeGoodsCount": 14991, "AwemeSalesGmv": 13886504.77, "AwemeSalesCount": 695100, "AwemeCount": 53515, "AwemeBloggerCount": 17645}, {"d": "06/10", "dt": "2026/06/10", "AwemeGoodsCount": 15244, "AwemeSalesGmv": 12696299.98, "AwemeSalesCount": 630930, "AwemeCount": 53111, "AwemeBloggerCount": 17491}, {"d": "06/11", "dt": "2026/06/11", "AwemeGoodsCount": 15355, "AwemeSalesGmv": 13310160.29, "AwemeSalesCount": 617192, "AwemeCount": 53702, "AwemeBloggerCount": 17235}, {"d": "06/12", "dt": "2026/06/12", "AwemeGoodsCount": 14450, "AwemeSalesGmv": 13187964.22, "AwemeSalesCount": 563350, "AwemeCount": 46605, "AwemeBloggerCount": 15747}, {"d": "06/13", "dt": "2026/06/13", "AwemeGoodsCount": 14947, "AwemeSalesGmv": 13363610.85, "AwemeSalesCount": 645906, "AwemeCount": 52166, "AwemeBloggerCount": 16576}, {"d": "06/14", "dt": "2026/06/14", "AwemeGoodsCount": 14228, "AwemeSalesGmv": 13220788.04, "AwemeSalesCount": 671653, "AwemeCount": 48676, "AwemeBloggerCount": 15871}, {"d": "06/15", "dt": "2026/06/15", "AwemeGoodsCount": 15039, "AwemeSalesGmv": 13337159.79, "AwemeSalesCount": 688979, "AwemeCount": 52135, "AwemeBloggerCount": 16750}, {"d": "06/16", "dt": "2026/06/16", "AwemeGoodsCount": 14884, "AwemeSalesGmv": 12569780.02, "AwemeSalesCount": 628164, "AwemeCount": 49773, "AwemeBloggerCount": 15966}, {"d": "06/17", "dt": "2026/06/17", "AwemeGoodsCount": 14758, "AwemeSalesGmv": 12427539.55, "AwemeSalesCount": 581943, "AwemeCount": 48750, "AwemeBloggerCount": 15467}, {"d": "06/18", "dt": "2026/06/18", "AwemeGoodsCount": 14370, "AwemeSalesGmv": 15527618.3, "AwemeSalesCount": 737621, "AwemeCount": 47123, "AwemeBloggerCount": 14522}, {"d": "06/19", "dt": "2026/06/19", "AwemeGoodsCount": 13758, "AwemeSalesGmv": 15926685.45, "AwemeSalesCount": 784063, "AwemeCount": 43422, "AwemeBloggerCount": 13588}, {"d": "06/20", "dt": "2026/06/20", "AwemeGoodsCount": 13488, "AwemeSalesGmv": 13708066.84, "AwemeSalesCount": 669050, "AwemeCount": 43286, "AwemeBloggerCount": 13720}, {"d": "06/21", "dt": "2026/06/21", "AwemeGoodsCount": 14047, "AwemeSalesGmv": 14707011.29, "AwemeSalesCount": 757345, "AwemeCount": 45396, "AwemeBloggerCount": 14266}, {"d": "06/22", "dt": "2026/06/22", "AwemeGoodsCount": 13626, "AwemeSalesGmv": 13239353.34, "AwemeSalesCount": 662125, "AwemeCount": 44109, "AwemeBloggerCount": 14583}, {"d": "06/23", "dt": "2026/06/23", "AwemeGoodsCount": 9074, "AwemeSalesGmv": 3218311.11, "AwemeSalesCount": 146316, "AwemeCount": 21073, "AwemeBloggerCount": 9124}], "90d": [{"d": "03/26", "dt": "2026/03/26", "AwemeGoodsCount": 13516, "AwemeSalesGmv": 11110923.16, "AwemeSalesCount": 604169, "AwemeCount": 45614, "AwemeBloggerCount": 14719}, {"d": "03/27", "dt": "2026/03/27", "AwemeGoodsCount": 13439, "AwemeSalesGmv": 10551026.75, "AwemeSalesCount": 537583, "AwemeCount": 45444, "AwemeBloggerCount": 14815}, {"d": "03/28", "dt": "2026/03/28", "AwemeGoodsCount": 12718, "AwemeSalesGmv": 10741167.63, "AwemeSalesCount": 558172, "AwemeCount": 42790, "AwemeBloggerCount": 13751}, {"d": "03/29", "dt": "2026/03/29", "AwemeGoodsCount": 12679, "AwemeSalesGmv": 10865753.52, "AwemeSalesCount": 559021, "AwemeCount": 41266, "AwemeBloggerCount": 13093}, {"d": "03/30", "dt": "2026/03/30", "AwemeGoodsCount": 13377, "AwemeSalesGmv": 9887926.17, "AwemeSalesCount": 525096, "AwemeCount": 45625, "AwemeBloggerCount": 14558}, {"d": "03/31", "dt": "2026/03/31", "AwemeGoodsCount": 13331, "AwemeSalesGmv": 9862928.97, "AwemeSalesCount": 493204, "AwemeCount": 44755, "AwemeBloggerCount": 14240}, {"d": "04/01", "dt": "2026/04/01", "AwemeGoodsCount": 13188, "AwemeSalesGmv": 9788980.32, "AwemeSalesCount": 469845, "AwemeCount": 43564, "AwemeBloggerCount": 13818}, {"d": "04/02", "dt": "2026/04/02", "AwemeGoodsCount": 13373, "AwemeSalesGmv": 9433309.69, "AwemeSalesCount": 450408, "AwemeCount": 44022, "AwemeBloggerCount": 13925}, {"d": "04/03", "dt": "2026/04/03", "AwemeGoodsCount": 13038, "AwemeSalesGmv": 9739765.87, "AwemeSalesCount": 480044, "AwemeCount": 43220, "AwemeBloggerCount": 13654}, {"d": "04/04", "dt": "2026/04/04", "AwemeGoodsCount": 11749, "AwemeSalesGmv": 9236000.85, "AwemeSalesCount": 466384, "AwemeCount": 36228, "AwemeBloggerCount": 11918}, {"d": "04/05", "dt": "2026/04/05", "AwemeGoodsCount": 11939, "AwemeSalesGmv": 10416796.14, "AwemeSalesCount": 555329, "AwemeCount": 39057, "AwemeBloggerCount": 11967}, {"d": "04/06", "dt": "2026/04/06", "AwemeGoodsCount": 12383, "AwemeSalesGmv": 9376001.83, "AwemeSalesCount": 504413, "AwemeCount": 40553, "AwemeBloggerCount": 12713}, {"d": "04/07", "dt": "2026/04/07", "AwemeGoodsCount": 11679, "AwemeSalesGmv": 7648538.58, "AwemeSalesCount": 429162, "AwemeCount": 37896, "AwemeBloggerCount": 12667}, {"d": "04/08", "dt": "2026/04/08", "AwemeGoodsCount": 13160, "AwemeSalesGmv": 9150336.72, "AwemeSalesCount": 456184, "AwemeCount": 44070, "AwemeBloggerCount": 13729}, {"d": "04/09", "dt": "2026/04/09", "AwemeGoodsCount": 13100, "AwemeSalesGmv": 9464994.28, "AwemeSalesCount": 457873, "AwemeCount": 42600, "AwemeBloggerCount": 13500}, {"d": "04/10", "dt": "2026/04/10", "AwemeGoodsCount": 13327, "AwemeSalesGmv": 10151195.7, "AwemeSalesCount": 512659, "AwemeCount": 43719, "AwemeBloggerCount": 13663}, {"d": "04/11", "dt": "2026/04/11", "AwemeGoodsCount": 13125, "AwemeSalesGmv": 11167191.47, "AwemeSalesCount": 553518, "AwemeCount": 41907, "AwemeBloggerCount": 13259}, {"d": "04/12", "dt": "2026/04/12", "AwemeGoodsCount": 13060, "AwemeSalesGmv": 13223398.11, "AwemeSalesCount": 743416, "AwemeCount": 42044, "AwemeBloggerCount": 12857}, {"d": "04/13", "dt": "2026/04/13", "AwemeGoodsCount": 13369, "AwemeSalesGmv": 10870404.99, "AwemeSalesCount": 586474, "AwemeCount": 43776, "AwemeBloggerCount": 13737}, {"d": "04/14", "dt": "2026/04/14", "AwemeGoodsCount": 13625, "AwemeSalesGmv": 10886809.76, "AwemeSalesCount": 504667, "AwemeCount": 42814, "AwemeBloggerCount": 13481}, {"d": "04/15", "dt": "2026/04/15", "AwemeGoodsCount": 13593, "AwemeSalesGmv": 11757861.37, "AwemeSalesCount": 537187, "AwemeCount": 44212, "AwemeBloggerCount": 13670}, {"d": "04/16", "dt": "2026/04/16", "AwemeGoodsCount": 13893, "AwemeSalesGmv": 11054072.82, "AwemeSalesCount": 510347, "AwemeCount": 45259, "AwemeBloggerCount": 14121}, {"d": "04/17", "dt": "2026/04/17", "AwemeGoodsCount": 13619, "AwemeSalesGmv": 10991442.03, "AwemeSalesCount": 479591, "AwemeCount": 44978, "AwemeBloggerCount": 13936}, {"d": "04/18", "dt": "2026/04/18", "AwemeGoodsCount": 13485, "AwemeSalesGmv": 12075696.81, "AwemeSalesCount": 508524, "AwemeCount": 43902, "AwemeBloggerCount": 13623}, {"d": "04/19", "dt": "2026/04/19", "AwemeGoodsCount": 12701, "AwemeSalesGmv": 10113792.43, "AwemeSalesCount": 417128, "AwemeCount": 37738, "AwemeBloggerCount": 12400}, {"d": "04/20", "dt": "2026/04/20", "AwemeGoodsCount": 13967, "AwemeSalesGmv": 10729840.13, "AwemeSalesCount": 497381, "AwemeCount": 45755, "AwemeBloggerCount": 14550}, {"d": "04/21", "dt": "2026/04/21", "AwemeGoodsCount": 13929, "AwemeSalesGmv": 11669542.82, "AwemeSalesCount": 516741, "AwemeCount": 46415, "AwemeBloggerCount": 14640}, {"d": "04/22", "dt": "2026/04/22", "AwemeGoodsCount": 14151, "AwemeSalesGmv": 12409151.37, "AwemeSalesCount": 557826, "AwemeCount": 46672, "AwemeBloggerCount": 14839}, {"d": "04/23", "dt": "2026/04/23", "AwemeGoodsCount": 13986, "AwemeSalesGmv": 12645704.6, "AwemeSalesCount": 581375, "AwemeCount": 46637, "AwemeBloggerCount": 14967}, {"d": "04/24", "dt": "2026/04/24", "AwemeGoodsCount": 13545, "AwemeSalesGmv": 11485613.81, "AwemeSalesCount": 454488, "AwemeCount": 43665, "AwemeBloggerCount": 14776}, {"d": "04/25", "dt": "2026/04/25", "AwemeGoodsCount": 13777, "AwemeSalesGmv": 12079544.62, "AwemeSalesCount": 572390, "AwemeCount": 46768, "AwemeBloggerCount": 15223}, {"d": "04/26", "dt": "2026/04/26", "AwemeGoodsCount": 13369, "AwemeSalesGmv": 11210294.87, "AwemeSalesCount": 555589, "AwemeCount": 44254, "AwemeBloggerCount": 14532}, {"d": "04/27", "dt": "2026/04/27", "AwemeGoodsCount": 13752, "AwemeSalesGmv": 10554117.23, "AwemeSalesCount": 477898, "AwemeCount": 45285, "AwemeBloggerCount": 14978}, {"d": "04/28", "dt": "2026/04/28", "AwemeGoodsCount": 14240, "AwemeSalesGmv": 10662017.32, "AwemeSalesCount": 482728, "AwemeCount": 47455, "AwemeBloggerCount": 15246}, {"d": "04/29", "dt": "2026/04/29", "AwemeGoodsCount": 13994, "AwemeSalesGmv": 9994175.32, "AwemeSalesCount": 438541, "AwemeCount": 47714, "AwemeBloggerCount": 14896}, {"d": "04/30", "dt": "2026/04/30", "AwemeGoodsCount": 13431, "AwemeSalesGmv": 9946467.04, "AwemeSalesCount": 480407, "AwemeCount": 45229, "AwemeBloggerCount": 14366}, {"d": "05/01", "dt": "2026/05/01", "AwemeGoodsCount": 12787, "AwemeSalesGmv": 10810416.0, "AwemeSalesCount": 520949, "AwemeCount": 41730, "AwemeBloggerCount": 13254}, {"d": "05/02", "dt": "2026/05/02", "AwemeGoodsCount": 12911, "AwemeSalesGmv": 10536213.45, "AwemeSalesCount": 493805, "AwemeCount": 42192, "AwemeBloggerCount": 13493}, {"d": "05/03", "dt": "2026/05/03", "AwemeGoodsCount": 13059, "AwemeSalesGmv": 10676176.78, "AwemeSalesCount": 503740, "AwemeCount": 43597, "AwemeBloggerCount": 13517}, {"d": "05/04", "dt": "2026/05/04", "AwemeGoodsCount": 13134, "AwemeSalesGmv": 10239498.91, "AwemeSalesCount": 477515, "AwemeCount": 44386, "AwemeBloggerCount": 14211}, {"d": "05/05", "dt": "2026/05/05", "AwemeGoodsCount": 13528, "AwemeSalesGmv": 10018947.36, "AwemeSalesCount": 465954, "AwemeCount": 45401, "AwemeBloggerCount": 14513}, {"d": "05/06", "dt": "2026/05/06", "AwemeGoodsCount": 13729, "AwemeSalesGmv": 9780193.93, "AwemeSalesCount": 452010, "AwemeCount": 46258, "AwemeBloggerCount": 14661}, {"d": "05/07", "dt": "2026/05/07", "AwemeGoodsCount": 13992, "AwemeSalesGmv": 10711109.17, "AwemeSalesCount": 477564, "AwemeCount": 46361, "AwemeBloggerCount": 14928}, {"d": "05/08", "dt": "2026/05/08", "AwemeGoodsCount": 13912, "AwemeSalesGmv": 12052795.23, "AwemeSalesCount": 549479, "AwemeCount": 46531, "AwemeBloggerCount": 14785}, {"d": "05/09", "dt": "2026/05/09", "AwemeGoodsCount": 13990, "AwemeSalesGmv": 11935308.86, "AwemeSalesCount": 568408, "AwemeCount": 47206, "AwemeBloggerCount": 14838}, {"d": "05/10", "dt": "2026/05/10", "AwemeGoodsCount": 13448, "AwemeSalesGmv": 12780364.99, "AwemeSalesCount": 600539, "AwemeCount": 45504, "AwemeBloggerCount": 14132}, {"d": "05/11", "dt": "2026/05/11", "AwemeGoodsCount": 14120, "AwemeSalesGmv": 11450427.0, "AwemeSalesCount": 533250, "AwemeCount": 47958, "AwemeBloggerCount": 15725}, {"d": "05/12", "dt": "2026/05/12", "AwemeGoodsCount": 14220, "AwemeSalesGmv": 12912279.12, "AwemeSalesCount": 585811, "AwemeCount": 47809, "AwemeBloggerCount": 15577}, {"d": "05/13", "dt": "2026/05/13", "AwemeGoodsCount": 14183, "AwemeSalesGmv": 11514277.64, "AwemeSalesCount": 514516, "AwemeCount": 46187, "AwemeBloggerCount": 15419}, {"d": "05/14", "dt": "2026/05/14", "AwemeGoodsCount": 14395, "AwemeSalesGmv": 13398925.1, "AwemeSalesCount": 556936, "AwemeCount": 48896, "AwemeBloggerCount": 15839}, {"d": "05/15", "dt": "2026/05/15", "AwemeGoodsCount": 14143, "AwemeSalesGmv": 14321232.42, "AwemeSalesCount": 547665, "AwemeCount": 47515, "AwemeBloggerCount": 15412}, {"d": "05/16", "dt": "2026/05/16", "AwemeGoodsCount": 14017, "AwemeSalesGmv": 15693531.77, "AwemeSalesCount": 594283, "AwemeCount": 47672, "AwemeBloggerCount": 15204}, {"d": "05/17", "dt": "2026/05/17", "AwemeGoodsCount": 14152, "AwemeSalesGmv": 16125362.53, "AwemeSalesCount": 666917, "AwemeCount": 47308, "AwemeBloggerCount": 14916}, {"d": "05/18", "dt": "2026/05/18", "AwemeGoodsCount": 14531, "AwemeSalesGmv": 13386850.22, "AwemeSalesCount": 612200, "AwemeCount": 50308, "AwemeBloggerCount": 16336}, {"d": "05/19", "dt": "2026/05/19", "AwemeGoodsCount": 14569, "AwemeSalesGmv": 12418757.39, "AwemeSalesCount": 584520, "AwemeCount": 49118, "AwemeBloggerCount": 16022}, {"d": "05/20", "dt": "2026/05/20", "AwemeGoodsCount": 14587, "AwemeSalesGmv": 12064610.14, "AwemeSalesCount": 596686, "AwemeCount": 49015, "AwemeBloggerCount": 15907}, {"d": "05/21", "dt": "2026/05/21", "AwemeGoodsCount": 14730, "AwemeSalesGmv": 12005805.1, "AwemeSalesCount": 592083, "AwemeCount": 49898, "AwemeBloggerCount": 15966}, {"d": "05/22", "dt": "2026/05/22", "AwemeGoodsCount": 14745, "AwemeSalesGmv": 12466460.84, "AwemeSalesCount": 620814, "AwemeCount": 49474, "AwemeBloggerCount": 15826}, {"d": "05/23", "dt": "2026/05/23", "AwemeGoodsCount": 14382, "AwemeSalesGmv": 12615727.15, "AwemeSalesCount": 654480, "AwemeCount": 48574, "AwemeBloggerCount": 15009}, {"d": "05/24", "dt": "2026/05/24", "AwemeGoodsCount": 13775, "AwemeSalesGmv": 12397338.35, "AwemeSalesCount": 663966, "AwemeCount": 46467, "AwemeBloggerCount": 14311}, {"d": "05/25", "dt": "2026/05/25", "AwemeGoodsCount": 14392, "AwemeSalesGmv": 12122516.7, "AwemeSalesCount": 629305, "AwemeCount": 49602, "AwemeBloggerCount": 15580}, {"d": "05/26", "dt": "2026/05/26", "AwemeGoodsCount": 14344, "AwemeSalesGmv": 14760977.88, "AwemeSalesCount": 785814, "AwemeCount": 50418, "AwemeBloggerCount": 15395}, {"d": "05/27", "dt": "2026/05/27", "AwemeGoodsCount": 14138, "AwemeSalesGmv": 11689323.46, "AwemeSalesCount": 570215, "AwemeCount": 48943, "AwemeBloggerCount": 15664}, {"d": "05/28", "dt": "2026/05/28", "AwemeGoodsCount": 14100, "AwemeSalesGmv": 11488653.04, "AwemeSalesCount": 562557, "AwemeCount": 47646, "AwemeBloggerCount": 15204}, {"d": "05/29", "dt": "2026/05/29", "AwemeGoodsCount": 14541, "AwemeSalesGmv": 13076147.88, "AwemeSalesCount": 678745, "AwemeCount": 50109, "AwemeBloggerCount": 15706}, {"d": "05/30", "dt": "2026/05/30", "AwemeGoodsCount": 14047, "AwemeSalesGmv": 13741023.71, "AwemeSalesCount": 658173, "AwemeCount": 48294, "AwemeBloggerCount": 15375}, {"d": "05/31", "dt": "2026/05/31", "AwemeGoodsCount": 13771, "AwemeSalesGmv": 12882437.21, "AwemeSalesCount": 612166, "AwemeCount": 47001, "AwemeBloggerCount": 15032}, {"d": "06/01", "dt": "2026/06/01", "AwemeGoodsCount": 14322, "AwemeSalesGmv": 12839070.13, "AwemeSalesCount": 633922, "AwemeCount": 49834, "AwemeBloggerCount": 15916}, {"d": "06/02", "dt": "2026/06/02", "AwemeGoodsCount": 14698, "AwemeSalesGmv": 14267777.11, "AwemeSalesCount": 610697, "AwemeCount": 50878, "AwemeBloggerCount": 16231}, {"d": "06/03", "dt": "2026/06/03", "AwemeGoodsCount": 14887, "AwemeSalesGmv": 13680347.07, "AwemeSalesCount": 628174, "AwemeCount": 51656, "AwemeBloggerCount": 16530}, {"d": "06/04", "dt": "2026/06/04", "AwemeGoodsCount": 14979, "AwemeSalesGmv": 13438610.97, "AwemeSalesCount": 668321, "AwemeCount": 51449, "AwemeBloggerCount": 16618}, {"d": "06/05", "dt": "2026/06/05", "AwemeGoodsCount": 14842, "AwemeSalesGmv": 14970736.34, "AwemeSalesCount": 806546, "AwemeCount": 53127, "AwemeBloggerCount": 16911}, {"d": "06/06", "dt": "2026/06/06", "AwemeGoodsCount": 14682, "AwemeSalesGmv": 15324780.42, "AwemeSalesCount": 712453, "AwemeCount": 52340, "AwemeBloggerCount": 16931}, {"d": "06/07", "dt": "2026/06/07", "AwemeGoodsCount": 14362, "AwemeSalesGmv": 14104597.36, "AwemeSalesCount": 602464, "AwemeCount": 49612, "AwemeBloggerCount": 16177}, {"d": "06/08", "dt": "2026/06/08", "AwemeGoodsCount": 14780, "AwemeSalesGmv": 12747114.89, "AwemeSalesCount": 576907, "AwemeCount": 51162, "AwemeBloggerCount": 17280}, {"d": "06/09", "dt": "2026/06/09", "AwemeGoodsCount": 14991, "AwemeSalesGmv": 13886504.77, "AwemeSalesCount": 695100, "AwemeCount": 53515, "AwemeBloggerCount": 17645}, {"d": "06/10", "dt": "2026/06/10", "AwemeGoodsCount": 15244, "AwemeSalesGmv": 12696299.98, "AwemeSalesCount": 630930, "AwemeCount": 53111, "AwemeBloggerCount": 17491}, {"d": "06/11", "dt": "2026/06/11", "AwemeGoodsCount": 15355, "AwemeSalesGmv": 13310160.29, "AwemeSalesCount": 617192, "AwemeCount": 53702, "AwemeBloggerCount": 17235}, {"d": "06/12", "dt": "2026/06/12", "AwemeGoodsCount": 14450, "AwemeSalesGmv": 13187964.22, "AwemeSalesCount": 563350, "AwemeCount": 46605, "AwemeBloggerCount": 15747}, {"d": "06/13", "dt": "2026/06/13", "AwemeGoodsCount": 14947, "AwemeSalesGmv": 13363610.85, "AwemeSalesCount": 645906, "AwemeCount": 52166, "AwemeBloggerCount": 16576}, {"d": "06/14", "dt": "2026/06/14", "AwemeGoodsCount": 14228, "AwemeSalesGmv": 13220788.04, "AwemeSalesCount": 671653, "AwemeCount": 48676, "AwemeBloggerCount": 15871}, {"d": "06/15", "dt": "2026/06/15", "AwemeGoodsCount": 15039, "AwemeSalesGmv": 13337159.79, "AwemeSalesCount": 688979, "AwemeCount": 52135, "AwemeBloggerCount": 16750}, {"d": "06/16", "dt": "2026/06/16", "AwemeGoodsCount": 14884, "AwemeSalesGmv": 12569780.02, "AwemeSalesCount": 628164, "AwemeCount": 49773, "AwemeBloggerCount": 15966}, {"d": "06/17", "dt": "2026/06/17", "AwemeGoodsCount": 14758, "AwemeSalesGmv": 12427539.55, "AwemeSalesCount": 581943, "AwemeCount": 48750, "AwemeBloggerCount": 15467}, {"d": "06/18", "dt": "2026/06/18", "AwemeGoodsCount": 14370, "AwemeSalesGmv": 15527618.3, "AwemeSalesCount": 737621, "AwemeCount": 47123, "AwemeBloggerCount": 14522}, {"d": "06/19", "dt": "2026/06/19", "AwemeGoodsCount": 13758, "AwemeSalesGmv": 15926685.45, "AwemeSalesCount": 784063, "AwemeCount": 43422, "AwemeBloggerCount": 13588}, {"d": "06/20", "dt": "2026/06/20", "AwemeGoodsCount": 13488, "AwemeSalesGmv": 13708066.84, "AwemeSalesCount": 669050, "AwemeCount": 43286, "AwemeBloggerCount": 13720}, {"d": "06/21", "dt": "2026/06/21", "AwemeGoodsCount": 14047, "AwemeSalesGmv": 14707011.29, "AwemeSalesCount": 757345, "AwemeCount": 45396, "AwemeBloggerCount": 14266}, {"d": "06/22", "dt": "2026/06/22", "AwemeGoodsCount": 13626, "AwemeSalesGmv": 13239353.34, "AwemeSalesCount": 662125, "AwemeCount": 44109, "AwemeBloggerCount": 14583}, {"d": "06/23", "dt": "2026/06/23", "AwemeGoodsCount": 9074, "AwemeSalesGmv": 3218311.11, "AwemeSalesCount": 146316, "AwemeCount": 21073, "AwemeBloggerCount": 9124}]}, "直播分析-trends": {"30d": [{"d": "05/25", "dt": "2026/05/25", "LiveGoodsCount": 219166, "LiveSalesGmv": 49696321.0, "LiveSalesCount": 1156903, "LiveCount": 47276, "LiveBloggerCount": 30434}, {"d": "05/26", "dt": "2026/05/26", "LiveGoodsCount": 229264, "LiveSalesGmv": 56723564.26, "LiveSalesCount": 1280517, "LiveCount": 49473, "LiveBloggerCount": 31700}, {"d": "05/27", "dt": "2026/05/27", "LiveGoodsCount": 228697, "LiveSalesGmv": 53809663.62, "LiveSalesCount": 1187088, "LiveCount": 50963, "LiveBloggerCount": 32502}, {"d": "05/28", "dt": "2026/05/28", "LiveGoodsCount": 233362, "LiveSalesGmv": 54441849.52, "LiveSalesCount": 1221175, "LiveCount": 51154, "LiveBloggerCount": 32547}, {"d": "05/29", "dt": "2026/05/29", "LiveGoodsCount": 231290, "LiveSalesGmv": 49917544.88, "LiveSalesCount": 1197874, "LiveCount": 50805, "LiveBloggerCount": 32472}, {"d": "05/30", "dt": "2026/05/30", "LiveGoodsCount": 225932, "LiveSalesGmv": 57736777.52, "LiveSalesCount": 1268974, "LiveCount": 48898, "LiveBloggerCount": 31314}, {"d": "05/31", "dt": "2026/05/31", "LiveGoodsCount": 212574, "LiveSalesGmv": 71381402.82, "LiveSalesCount": 1265089, "LiveCount": 46576, "LiveBloggerCount": 30006}, {"d": "06/01", "dt": "2026/06/01", "LiveGoodsCount": 203248, "LiveSalesGmv": 53903677.21, "LiveSalesCount": 995824, "LiveCount": 46843, "LiveBloggerCount": 30170}, {"d": "06/02", "dt": "2026/06/02", "LiveGoodsCount": 226054, "LiveSalesGmv": 57832289.9, "LiveSalesCount": 1176528, "LiveCount": 50360, "LiveBloggerCount": 32553}, {"d": "06/03", "dt": "2026/06/03", "LiveGoodsCount": 232771, "LiveSalesGmv": 61915312.55, "LiveSalesCount": 1226492, "LiveCount": 51485, "LiveBloggerCount": 32881}, {"d": "06/04", "dt": "2026/06/04", "LiveGoodsCount": 231581, "LiveSalesGmv": 66923774.95, "LiveSalesCount": 1232953, "LiveCount": 51655, "LiveBloggerCount": 33016}, {"d": "06/05", "dt": "2026/06/05", "LiveGoodsCount": 230998, "LiveSalesGmv": 63229028.66, "LiveSalesCount": 1301075, "LiveCount": 52045, "LiveBloggerCount": 33080}, {"d": "06/06", "dt": "2026/06/06", "LiveGoodsCount": 222749, "LiveSalesGmv": 90792179.72, "LiveSalesCount": 1466799, "LiveCount": 50593, "LiveBloggerCount": 32183}, {"d": "06/07", "dt": "2026/06/07", "LiveGoodsCount": 214771, "LiveSalesGmv": 87479419.29, "LiveSalesCount": 1437209, "LiveCount": 48690, "LiveBloggerCount": 31126}, {"d": "06/08", "dt": "2026/06/08", "LiveGoodsCount": 213169, "LiveSalesGmv": 62966532.48, "LiveSalesCount": 1179906, "LiveCount": 50085, "LiveBloggerCount": 32019}, {"d": "06/09", "dt": "2026/06/09", "LiveGoodsCount": 225773, "LiveSalesGmv": 75223344.28, "LiveSalesCount": 1248062, "LiveCount": 52616, "LiveBloggerCount": 33737}, {"d": "06/10", "dt": "2026/06/10", "LiveGoodsCount": 228520, "LiveSalesGmv": 56114890.13, "LiveSalesCount": 1303929, "LiveCount": 53316, "LiveBloggerCount": 34363}, {"d": "06/11", "dt": "2026/06/11", "LiveGoodsCount": 233087, "LiveSalesGmv": 56331177.67, "LiveSalesCount": 1258653, "LiveCount": 55075, "LiveBloggerCount": 35484}, {"d": "06/12", "dt": "2026/06/12", "LiveGoodsCount": 235661, "LiveSalesGmv": 58138320.66, "LiveSalesCount": 1278808, "LiveCount": 54655, "LiveBloggerCount": 35239}, {"d": "06/13", "dt": "2026/06/13", "LiveGoodsCount": 226668, "LiveSalesGmv": 64791396.89, "LiveSalesCount": 1359808, "LiveCount": 52278, "LiveBloggerCount": 33865}, {"d": "06/14", "dt": "2026/06/14", "LiveGoodsCount": 217509, "LiveSalesGmv": 83129045.35, "LiveSalesCount": 1436238, "LiveCount": 50378, "LiveBloggerCount": 32682}, {"d": "06/15", "dt": "2026/06/15", "LiveGoodsCount": 219466, "LiveSalesGmv": 55886391.58, "LiveSalesCount": 1204838, "LiveCount": 52100, "LiveBloggerCount": 33781}, {"d": "06/16", "dt": "2026/06/16", "LiveGoodsCount": 234420, "LiveSalesGmv": 58403651.76, "LiveSalesCount": 1213054, "LiveCount": 54025, "LiveBloggerCount": 35154}, {"d": "06/17", "dt": "2026/06/17", "LiveGoodsCount": 234228, "LiveSalesGmv": 57653924.79, "LiveSalesCount": 1181969, "LiveCount": 54430, "LiveBloggerCount": 35346}, {"d": "06/18", "dt": "2026/06/18", "LiveGoodsCount": 229592, "LiveSalesGmv": 56443931.65, "LiveSalesCount": 1135138, "LiveCount": 52121, "LiveBloggerCount": 33996}, {"d": "06/19", "dt": "2026/06/19", "LiveGoodsCount": 194410, "LiveSalesGmv": 57117106.4, "LiveSalesCount": 1251427, "LiveCount": 42630, "LiveBloggerCount": 28304}, {"d": "06/20", "dt": "2026/06/20", "LiveGoodsCount": 211438, "LiveSalesGmv": 51611509.5, "LiveSalesCount": 1129500, "LiveCount": 46537, "LiveBloggerCount": 30612}, {"d": "06/21", "dt": "2026/06/21", "LiveGoodsCount": 222336, "LiveSalesGmv": 57708774.57, "LiveSalesCount": 1337991, "LiveCount": 49512, "LiveBloggerCount": 32031}, {"d": "06/22", "dt": "2026/06/22", "LiveGoodsCount": 229129, "LiveSalesGmv": 49767667.76, "LiveSalesCount": 1160998, "LiveCount": 51689, "LiveBloggerCount": 33642}, {"d": "06/23", "dt": "2026/06/23", "LiveGoodsCount": 237191, "LiveSalesGmv": 51938890.45, "LiveSalesCount": 1109069, "LiveCount": 52252, "LiveBloggerCount": 34178}], "90d": [{"d": "03/26", "dt": "2026/03/26", "LiveGoodsCount": 189584, "LiveSalesGmv": 48720945.89, "LiveSalesCount": 1053939, "LiveCount": 45409, "LiveBloggerCount": 27035}, {"d": "03/27", "dt": "2026/03/27", "LiveGoodsCount": 188659, "LiveSalesGmv": 50142048.12, "LiveSalesCount": 1065761, "LiveCount": 45379, "LiveBloggerCount": 27029}, {"d": "03/28", "dt": "2026/03/28", "LiveGoodsCount": 181146, "LiveSalesGmv": 57076550.6, "LiveSalesCount": 1155771, "LiveCount": 43312, "LiveBloggerCount": 25758}, {"d": "03/29", "dt": "2026/03/29", "LiveGoodsCount": 179315, "LiveSalesGmv": 66172418.43, "LiveSalesCount": 1314243, "LiveCount": 42190, "LiveBloggerCount": 24849}, {"d": "03/30", "dt": "2026/03/30", "LiveGoodsCount": 182713, "LiveSalesGmv": 43154177.24, "LiveSalesCount": 936032, "LiveCount": 45369, "LiveBloggerCount": 26549}, {"d": "03/31", "dt": "2026/03/31", "LiveGoodsCount": 187440, "LiveSalesGmv": 52988857.67, "LiveSalesCount": 1348654, "LiveCount": 47239, "LiveBloggerCount": 27741}, {"d": "04/01", "dt": "2026/04/01", "LiveGoodsCount": 187721, "LiveSalesGmv": 46587083.86, "LiveSalesCount": 1013485, "LiveCount": 47120, "LiveBloggerCount": 27432}, {"d": "04/02", "dt": "2026/04/02", "LiveGoodsCount": 191669, "LiveSalesGmv": 49523272.59, "LiveSalesCount": 1068371, "LiveCount": 47648, "LiveBloggerCount": 27615}, {"d": "04/03", "dt": "2026/04/03", "LiveGoodsCount": 189688, "LiveSalesGmv": 48771268.06, "LiveSalesCount": 1050678, "LiveCount": 47245, "LiveBloggerCount": 27271}, {"d": "04/04", "dt": "2026/04/04", "LiveGoodsCount": 173658, "LiveSalesGmv": 51144276.64, "LiveSalesCount": 1106032, "LiveCount": 43520, "LiveBloggerCount": 25016}, {"d": "04/05", "dt": "2026/04/05", "LiveGoodsCount": 155011, "LiveSalesGmv": 46879339.65, "LiveSalesCount": 1108073, "LiveCount": 40109, "LiveBloggerCount": 22691}, {"d": "04/06", "dt": "2026/04/06", "LiveGoodsCount": 175652, "LiveSalesGmv": 50219988.4, "LiveSalesCount": 1172879, "LiveCount": 43580, "LiveBloggerCount": 25225}, {"d": "04/07", "dt": "2026/04/07", "LiveGoodsCount": 192468, "LiveSalesGmv": 48772383.79, "LiveSalesCount": 1054348, "LiveCount": 47604, "LiveBloggerCount": 28148}, {"d": "04/08", "dt": "2026/04/08", "LiveGoodsCount": 205054, "LiveSalesGmv": 47521539.33, "LiveSalesCount": 1090560, "LiveCount": 48851, "LiveBloggerCount": 29262}, {"d": "04/09", "dt": "2026/04/09", "LiveGoodsCount": 208555, "LiveSalesGmv": 52631923.03, "LiveSalesCount": 1103617, "LiveCount": 49111, "LiveBloggerCount": 29346}, {"d": "04/10", "dt": "2026/04/10", "LiveGoodsCount": 207252, "LiveSalesGmv": 49798933.04, "LiveSalesCount": 1086746, "LiveCount": 49357, "LiveBloggerCount": 29453}, {"d": "04/11", "dt": "2026/04/11", "LiveGoodsCount": 196791, "LiveSalesGmv": 56733495.71, "LiveSalesCount": 1178943, "LiveCount": 47354, "LiveBloggerCount": 28204}, {"d": "04/12", "dt": "2026/04/12", "LiveGoodsCount": 190741, "LiveSalesGmv": 59180789.09, "LiveSalesCount": 1273647, "LiveCount": 45907, "LiveBloggerCount": 27338}, {"d": "04/13", "dt": "2026/04/13", "LiveGoodsCount": 194034, "LiveSalesGmv": 44373548.64, "LiveSalesCount": 982779, "LiveCount": 47280, "LiveBloggerCount": 28179}, {"d": "04/14", "dt": "2026/04/14", "LiveGoodsCount": 206011, "LiveSalesGmv": 50704894.02, "LiveSalesCount": 1082224, "LiveCount": 49741, "LiveBloggerCount": 29750}, {"d": "04/15", "dt": "2026/04/15", "LiveGoodsCount": 203674, "LiveSalesGmv": 49233301.72, "LiveSalesCount": 1051320, "LiveCount": 51553, "LiveBloggerCount": 29984}, {"d": "04/16", "dt": "2026/04/16", "LiveGoodsCount": 206906, "LiveSalesGmv": 55250565.18, "LiveSalesCount": 1091725, "LiveCount": 51096, "LiveBloggerCount": 29247}, {"d": "04/17", "dt": "2026/04/17", "LiveGoodsCount": 207955, "LiveSalesGmv": 50481792.07, "LiveSalesCount": 1088901, "LiveCount": 51644, "LiveBloggerCount": 29535}, {"d": "04/18", "dt": "2026/04/18", "LiveGoodsCount": 203571, "LiveSalesGmv": 55558637.14, "LiveSalesCount": 1157644, "LiveCount": 48481, "LiveBloggerCount": 27417}, {"d": "04/19", "dt": "2026/04/19", "LiveGoodsCount": 194710, "LiveSalesGmv": 57427264.99, "LiveSalesCount": 1173482, "LiveCount": 48693, "LiveBloggerCount": 26890}, {"d": "04/20", "dt": "2026/04/20", "LiveGoodsCount": 198616, "LiveSalesGmv": 44707731.96, "LiveSalesCount": 978710, "LiveCount": 50408, "LiveBloggerCount": 28163}, {"d": "04/21", "dt": "2026/04/21", "LiveGoodsCount": 211434, "LiveSalesGmv": 60464867.09, "LiveSalesCount": 1162159, "LiveCount": 52028, "LiveBloggerCount": 29399}, {"d": "04/22", "dt": "2026/04/22", "LiveGoodsCount": 214307, "LiveSalesGmv": 62804676.43, "LiveSalesCount": 1285659, "LiveCount": 51263, "LiveBloggerCount": 29935}, {"d": "04/23", "dt": "2026/04/23", "LiveGoodsCount": 214985, "LiveSalesGmv": 55666264.23, "LiveSalesCount": 1156735, "LiveCount": 50216, "LiveBloggerCount": 30142}, {"d": "04/24", "dt": "2026/04/24", "LiveGoodsCount": 216222, "LiveSalesGmv": 53647797.32, "LiveSalesCount": 1168979, "LiveCount": 53324, "LiveBloggerCount": 30897}, {"d": "04/25", "dt": "2026/04/25", "LiveGoodsCount": 209336, "LiveSalesGmv": 58261156.94, "LiveSalesCount": 1179342, "LiveCount": 51844, "LiveBloggerCount": 29582}, {"d": "04/26", "dt": "2026/04/26", "LiveGoodsCount": 205328, "LiveSalesGmv": 67358398.2, "LiveSalesCount": 1197655, "LiveCount": 51843, "LiveBloggerCount": 29106}, {"d": "04/27", "dt": "2026/04/27", "LiveGoodsCount": 209867, "LiveSalesGmv": 45966382.94, "LiveSalesCount": 987108, "LiveCount": 54121, "LiveBloggerCount": 30393}, {"d": "04/28", "dt": "2026/04/28", "LiveGoodsCount": 218745, "LiveSalesGmv": 53319036.07, "LiveSalesCount": 1097379, "LiveCount": 54829, "LiveBloggerCount": 31298}, {"d": "04/29", "dt": "2026/04/29", "LiveGoodsCount": 222523, "LiveSalesGmv": 49679244.3, "LiveSalesCount": 1079429, "LiveCount": 54351, "LiveBloggerCount": 31101}, {"d": "04/30", "dt": "2026/04/30", "LiveGoodsCount": 215178, "LiveSalesGmv": 44652837.19, "LiveSalesCount": 949641, "LiveCount": 51477, "LiveBloggerCount": 28813}, {"d": "05/01", "dt": "2026/05/01", "LiveGoodsCount": 181735, "LiveSalesGmv": 48836081.57, "LiveSalesCount": 1030437, "LiveCount": 45998, "LiveBloggerCount": 24958}, {"d": "05/02", "dt": "2026/05/02", "LiveGoodsCount": 183341, "LiveSalesGmv": 52321849.16, "LiveSalesCount": 1091196, "LiveCount": 47278, "LiveBloggerCount": 25184}, {"d": "05/03", "dt": "2026/05/03", "LiveGoodsCount": 188568, "LiveSalesGmv": 56312326.53, "LiveSalesCount": 1059405, "LiveCount": 48236, "LiveBloggerCount": 26023}, {"d": "05/04", "dt": "2026/05/04", "LiveGoodsCount": 195276, "LiveSalesGmv": 48377408.84, "LiveSalesCount": 1048817, "LiveCount": 49055, "LiveBloggerCount": 26583}, {"d": "05/05", "dt": "2026/05/05", "LiveGoodsCount": 206849, "LiveSalesGmv": 54494538.73, "LiveSalesCount": 1120470, "LiveCount": 50844, "LiveBloggerCount": 28069}, {"d": "05/06", "dt": "2026/05/06", "LiveGoodsCount": 214409, "LiveSalesGmv": 55553627.97, "LiveSalesCount": 1081304, "LiveCount": 54267, "LiveBloggerCount": 30288}, {"d": "05/07", "dt": "2026/05/07", "LiveGoodsCount": 222827, "LiveSalesGmv": 57044477.03, "LiveSalesCount": 1169200, "LiveCount": 55656, "LiveBloggerCount": 31112}, {"d": "05/08", "dt": "2026/05/08", "LiveGoodsCount": 227873, "LiveSalesGmv": 61383413.93, "LiveSalesCount": 1242261, "LiveCount": 56729, "LiveBloggerCount": 31720}, {"d": "05/09", "dt": "2026/05/09", "LiveGoodsCount": 223823, "LiveSalesGmv": 63928784.33, "LiveSalesCount": 1290167, "LiveCount": 55385, "LiveBloggerCount": 30480}, {"d": "05/10", "dt": "2026/05/10", "LiveGoodsCount": 209885, "LiveSalesGmv": 65430585.07, "LiveSalesCount": 1353714, "LiveCount": 54613, "LiveBloggerCount": 28580}, {"d": "05/11", "dt": "2026/05/11", "LiveGoodsCount": 212038, "LiveSalesGmv": 53185984.5, "LiveSalesCount": 1059100, "LiveCount": 57781, "LiveBloggerCount": 30383}, {"d": "05/12", "dt": "2026/05/12", "LiveGoodsCount": 219686, "LiveSalesGmv": 57995457.21, "LiveSalesCount": 1158673, "LiveCount": 56189, "LiveBloggerCount": 31362}, {"d": "05/13", "dt": "2026/05/13", "LiveGoodsCount": 222583, "LiveSalesGmv": 58239649.14, "LiveSalesCount": 1209519, "LiveCount": 56916, "LiveBloggerCount": 31579}, {"d": "05/14", "dt": "2026/05/14", "LiveGoodsCount": 226298, "LiveSalesGmv": 57163215.09, "LiveSalesCount": 1238030, "LiveCount": 58623, "LiveBloggerCount": 31858}, {"d": "05/15", "dt": "2026/05/15", "LiveGoodsCount": 224755, "LiveSalesGmv": 61301521.18, "LiveSalesCount": 1207153, "LiveCount": 56153, "LiveBloggerCount": 32093}, {"d": "05/16", "dt": "2026/05/16", "LiveGoodsCount": 217182, "LiveSalesGmv": 66122331.19, "LiveSalesCount": 1349569, "LiveCount": 52090, "LiveBloggerCount": 30128}, {"d": "05/17", "dt": "2026/05/17", "LiveGoodsCount": 208916, "LiveSalesGmv": 74960992.88, "LiveSalesCount": 1477316, "LiveCount": 51475, "LiveBloggerCount": 29726}, {"d": "05/18", "dt": "2026/05/18", "LiveGoodsCount": 207851, "LiveSalesGmv": 58573150.36, "LiveSalesCount": 1166281, "LiveCount": 51853, "LiveBloggerCount": 30519}, {"d": "05/19", "dt": "2026/05/19", "LiveGoodsCount": 229658, "LiveSalesGmv": 60672273.16, "LiveSalesCount": 1250481, "LiveCount": 50691, "LiveBloggerCount": 32213}, {"d": "05/20", "dt": "2026/05/20", "LiveGoodsCount": 231314, "LiveSalesGmv": 64269955.33, "LiveSalesCount": 1240490, "LiveCount": 47480, "LiveBloggerCount": 31976}, {"d": "05/21", "dt": "2026/05/21", "LiveGoodsCount": 229366, "LiveSalesGmv": 60808250.19, "LiveSalesCount": 1336325, "LiveCount": 45941, "LiveBloggerCount": 30765}, {"d": "05/22", "dt": "2026/05/22", "LiveGoodsCount": 234826, "LiveSalesGmv": 55423057.23, "LiveSalesCount": 1324220, "LiveCount": 48852, "LiveBloggerCount": 31939}, {"d": "05/23", "dt": "2026/05/23", "LiveGoodsCount": 228966, "LiveSalesGmv": 60279528.33, "LiveSalesCount": 1354015, "LiveCount": 47281, "LiveBloggerCount": 30578}, {"d": "05/24", "dt": "2026/05/24", "LiveGoodsCount": 215933, "LiveSalesGmv": 60678626.91, "LiveSalesCount": 1334461, "LiveCount": 44841, "LiveBloggerCount": 29044}, {"d": "05/25", "dt": "2026/05/25", "LiveGoodsCount": 219166, "LiveSalesGmv": 49696321.0, "LiveSalesCount": 1156903, "LiveCount": 47276, "LiveBloggerCount": 30434}, {"d": "05/26", "dt": "2026/05/26", "LiveGoodsCount": 229264, "LiveSalesGmv": 56723564.26, "LiveSalesCount": 1280517, "LiveCount": 49473, "LiveBloggerCount": 31700}, {"d": "05/27", "dt": "2026/05/27", "LiveGoodsCount": 228697, "LiveSalesGmv": 53809663.62, "LiveSalesCount": 1187088, "LiveCount": 50963, "LiveBloggerCount": 32502}, {"d": "05/28", "dt": "2026/05/28", "LiveGoodsCount": 233362, "LiveSalesGmv": 54441849.52, "LiveSalesCount": 1221175, "LiveCount": 51154, "LiveBloggerCount": 32547}, {"d": "05/29", "dt": "2026/05/29", "LiveGoodsCount": 231290, "LiveSalesGmv": 49917544.88, "LiveSalesCount": 1197874, "LiveCount": 50805, "LiveBloggerCount": 32472}, {"d": "05/30", "dt": "2026/05/30", "LiveGoodsCount": 225932, "LiveSalesGmv": 57736777.52, "LiveSalesCount": 1268974, "LiveCount": 48898, "LiveBloggerCount": 31314}, {"d": "05/31", "dt": "2026/05/31", "LiveGoodsCount": 212574, "LiveSalesGmv": 71381402.82, "LiveSalesCount": 1265089, "LiveCount": 46576, "LiveBloggerCount": 30006}, {"d": "06/01", "dt": "2026/06/01", "LiveGoodsCount": 203248, "LiveSalesGmv": 53903677.21, "LiveSalesCount": 995824, "LiveCount": 46843, "LiveBloggerCount": 30170}, {"d": "06/02", "dt": "2026/06/02", "LiveGoodsCount": 226054, "LiveSalesGmv": 57832289.9, "LiveSalesCount": 1176528, "LiveCount": 50360, "LiveBloggerCount": 32553}, {"d": "06/03", "dt": "2026/06/03", "LiveGoodsCount": 232771, "LiveSalesGmv": 61915312.55, "LiveSalesCount": 1226492, "LiveCount": 51485, "LiveBloggerCount": 32881}, {"d": "06/04", "dt": "2026/06/04", "LiveGoodsCount": 231581, "LiveSalesGmv": 66923774.95, "LiveSalesCount": 1232953, "LiveCount": 51655, "LiveBloggerCount": 33016}, {"d": "06/05", "dt": "2026/06/05", "LiveGoodsCount": 230998, "LiveSalesGmv": 63229028.66, "LiveSalesCount": 1301075, "LiveCount": 52045, "LiveBloggerCount": 33080}, {"d": "06/06", "dt": "2026/06/06", "LiveGoodsCount": 222749, "LiveSalesGmv": 90792179.72, "LiveSalesCount": 1466799, "LiveCount": 50593, "LiveBloggerCount": 32183}, {"d": "06/07", "dt": "2026/06/07", "LiveGoodsCount": 214771, "LiveSalesGmv": 87479419.29, "LiveSalesCount": 1437209, "LiveCount": 48690, "LiveBloggerCount": 31126}, {"d": "06/08", "dt": "2026/06/08", "LiveGoodsCount": 213169, "LiveSalesGmv": 62966532.48, "LiveSalesCount": 1179906, "LiveCount": 50085, "LiveBloggerCount": 32019}, {"d": "06/09", "dt": "2026/06/09", "LiveGoodsCount": 225773, "LiveSalesGmv": 75223344.28, "LiveSalesCount": 1248062, "LiveCount": 52616, "LiveBloggerCount": 33737}, {"d": "06/10", "dt": "2026/06/10", "LiveGoodsCount": 228520, "LiveSalesGmv": 56114890.13, "LiveSalesCount": 1303929, "LiveCount": 53316, "LiveBloggerCount": 34363}, {"d": "06/11", "dt": "2026/06/11", "LiveGoodsCount": 233087, "LiveSalesGmv": 56331177.67, "LiveSalesCount": 1258653, "LiveCount": 55075, "LiveBloggerCount": 35484}, {"d": "06/12", "dt": "2026/06/12", "LiveGoodsCount": 235661, "LiveSalesGmv": 58138320.66, "LiveSalesCount": 1278808, "LiveCount": 54655, "LiveBloggerCount": 35239}, {"d": "06/13", "dt": "2026/06/13", "LiveGoodsCount": 226668, "LiveSalesGmv": 64791396.89, "LiveSalesCount": 1359808, "LiveCount": 52278, "LiveBloggerCount": 33865}, {"d": "06/14", "dt": "2026/06/14", "LiveGoodsCount": 217509, "LiveSalesGmv": 83129045.35, "LiveSalesCount": 1436238, "LiveCount": 50378, "LiveBloggerCount": 32682}, {"d": "06/15", "dt": "2026/06/15", "LiveGoodsCount": 219466, "LiveSalesGmv": 55886391.58, "LiveSalesCount": 1204838, "LiveCount": 52100, "LiveBloggerCount": 33781}, {"d": "06/16", "dt": "2026/06/16", "LiveGoodsCount": 234420, "LiveSalesGmv": 58403651.76, "LiveSalesCount": 1213054, "LiveCount": 54025, "LiveBloggerCount": 35154}, {"d": "06/17", "dt": "2026/06/17", "LiveGoodsCount": 234228, "LiveSalesGmv": 57653924.79, "LiveSalesCount": 1181969, "LiveCount": 54430, "LiveBloggerCount": 35346}, {"d": "06/18", "dt": "2026/06/18", "LiveGoodsCount": 229592, "LiveSalesGmv": 56443931.65, "LiveSalesCount": 1135138, "LiveCount": 52121, "LiveBloggerCount": 33996}, {"d": "06/19", "dt": "2026/06/19", "LiveGoodsCount": 194410, "LiveSalesGmv": 57117106.4, "LiveSalesCount": 1251427, "LiveCount": 42630, "LiveBloggerCount": 28304}, {"d": "06/20", "dt": "2026/06/20", "LiveGoodsCount": 211438, "LiveSalesGmv": 51611509.5, "LiveSalesCount": 1129500, "LiveCount": 46537, "LiveBloggerCount": 30612}, {"d": "06/21", "dt": "2026/06/21", "LiveGoodsCount": 222336, "LiveSalesGmv": 57708774.57, "LiveSalesCount": 1337991, "LiveCount": 49512, "LiveBloggerCount": 32031}, {"d": "06/22", "dt": "2026/06/22", "LiveGoodsCount": 229129, "LiveSalesGmv": 49767667.76, "LiveSalesCount": 1160998, "LiveCount": 51689, "LiveBloggerCount": 33642}, {"d": "06/23", "dt": "2026/06/23", "LiveGoodsCount": 237191, "LiveSalesGmv": 51938890.45, "LiveSalesCount": 1109069, "LiveCount": 52252, "LiveBloggerCount": 34178}]}, "达人分析-trends": {"30d": [{"d": "05/25", "dt": "2026/05/25", "AwemeBloggerCount": 15580, "LiveBloggerCount": 30434, "BloggerCount": 45310}, {"d": "05/26", "dt": "2026/05/26", "AwemeBloggerCount": 15395, "LiveBloggerCount": 31700, "BloggerCount": 46363}, {"d": "05/27", "dt": "2026/05/27", "AwemeBloggerCount": 15664, "LiveBloggerCount": 32502, "BloggerCount": 47454}, {"d": "05/28", "dt": "2026/05/28", "AwemeBloggerCount": 15204, "LiveBloggerCount": 32547, "BloggerCount": 47066}, {"d": "05/29", "dt": "2026/05/29", "AwemeBloggerCount": 15706, "LiveBloggerCount": 32472, "BloggerCount": 47455}, {"d": "05/30", "dt": "2026/05/30", "AwemeBloggerCount": 15375, "LiveBloggerCount": 31314, "BloggerCount": 46051}, {"d": "05/31", "dt": "2026/05/31", "AwemeBloggerCount": 15032, "LiveBloggerCount": 30006, "BloggerCount": 44422}, {"d": "06/01", "dt": "2026/06/01", "AwemeBloggerCount": 15916, "LiveBloggerCount": 30170, "BloggerCount": 45451}, {"d": "06/02", "dt": "2026/06/02", "AwemeBloggerCount": 16231, "LiveBloggerCount": 32553, "BloggerCount": 48039}, {"d": "06/03", "dt": "2026/06/03", "AwemeBloggerCount": 16530, "LiveBloggerCount": 32881, "BloggerCount": 48658}, {"d": "06/04", "dt": "2026/06/04", "AwemeBloggerCount": 16618, "LiveBloggerCount": 33016, "BloggerCount": 48847}, {"d": "06/05", "dt": "2026/06/05", "AwemeBloggerCount": 16911, "LiveBloggerCount": 33080, "BloggerCount": 49248}, {"d": "06/06", "dt": "2026/06/06", "AwemeBloggerCount": 16931, "LiveBloggerCount": 32183, "BloggerCount": 48435}, {"d": "06/07", "dt": "2026/06/07", "AwemeBloggerCount": 16177, "LiveBloggerCount": 31126, "BloggerCount": 46620}, {"d": "06/08", "dt": "2026/06/08", "AwemeBloggerCount": 17280, "LiveBloggerCount": 32019, "BloggerCount": 48598}, {"d": "06/09", "dt": "2026/06/09", "AwemeBloggerCount": 17645, "LiveBloggerCount": 33737, "BloggerCount": 50631}, {"d": "06/10", "dt": "2026/06/10", "AwemeBloggerCount": 17491, "LiveBloggerCount": 34363, "BloggerCount": 51113}, {"d": "06/11", "dt": "2026/06/11", "AwemeBloggerCount": 17235, "LiveBloggerCount": 35484, "BloggerCount": 51967}, {"d": "06/12", "dt": "2026/06/12", "AwemeBloggerCount": 15747, "LiveBloggerCount": 35239, "BloggerCount": 50293}, {"d": "06/13", "dt": "2026/06/13", "AwemeBloggerCount": 16576, "LiveBloggerCount": 33865, "BloggerCount": 49726}, {"d": "06/14", "dt": "2026/06/14", "AwemeBloggerCount": 15871, "LiveBloggerCount": 32682, "BloggerCount": 47908}, {"d": "06/15", "dt": "2026/06/15", "AwemeBloggerCount": 16750, "LiveBloggerCount": 33781, "BloggerCount": 49809}, {"d": "06/16", "dt": "2026/06/16", "AwemeBloggerCount": 15966, "LiveBloggerCount": 35154, "BloggerCount": 50396}, {"d": "06/17", "dt": "2026/06/17", "AwemeBloggerCount": 15467, "LiveBloggerCount": 35346, "BloggerCount": 50101}, {"d": "06/18", "dt": "2026/06/18", "AwemeBloggerCount": 14522, "LiveBloggerCount": 33996, "BloggerCount": 47858}, {"d": "06/19", "dt": "2026/06/19", "AwemeBloggerCount": 13588, "LiveBloggerCount": 28304, "BloggerCount": 41357}, {"d": "06/20", "dt": "2026/06/20", "AwemeBloggerCount": 13720, "LiveBloggerCount": 30612, "BloggerCount": 43750}, {"d": "06/21", "dt": "2026/06/21", "AwemeBloggerCount": 14266, "LiveBloggerCount": 32031, "BloggerCount": 45685}, {"d": "06/22", "dt": "2026/06/22", "AwemeBloggerCount": 14583, "LiveBloggerCount": 33642, "BloggerCount": 47576}, {"d": "06/23", "dt": "2026/06/23", "AwemeBloggerCount": 9124, "LiveBloggerCount": 34178, "BloggerCount": 42810}], "90d": [{"d": "03/26", "dt": "2026/03/26", "AwemeBloggerCount": 14719, "LiveBloggerCount": 27035, "BloggerCount": 41138}, {"d": "03/27", "dt": "2026/03/27", "AwemeBloggerCount": 14815, "LiveBloggerCount": 27029, "BloggerCount": 41218}, {"d": "03/28", "dt": "2026/03/28", "AwemeBloggerCount": 13751, "LiveBloggerCount": 25758, "BloggerCount": 38967}, {"d": "03/29", "dt": "2026/03/29", "AwemeBloggerCount": 13093, "LiveBloggerCount": 24849, "BloggerCount": 37389}, {"d": "03/30", "dt": "2026/03/30", "AwemeBloggerCount": 14558, "LiveBloggerCount": 26549, "BloggerCount": 40486}, {"d": "03/31", "dt": "2026/03/31", "AwemeBloggerCount": 14240, "LiveBloggerCount": 27741, "BloggerCount": 41362}, {"d": "04/01", "dt": "2026/04/01", "AwemeBloggerCount": 13818, "LiveBloggerCount": 27432, "BloggerCount": 40666}, {"d": "04/02", "dt": "2026/04/02", "AwemeBloggerCount": 13925, "LiveBloggerCount": 27615, "BloggerCount": 40898}, {"d": "04/03", "dt": "2026/04/03", "AwemeBloggerCount": 13654, "LiveBloggerCount": 27271, "BloggerCount": 40334}, {"d": "04/04", "dt": "2026/04/04", "AwemeBloggerCount": 11918, "LiveBloggerCount": 25016, "BloggerCount": 36413}, {"d": "04/05", "dt": "2026/04/05", "AwemeBloggerCount": 11967, "LiveBloggerCount": 22691, "BloggerCount": 34206}, {"d": "04/06", "dt": "2026/04/06", "AwemeBloggerCount": 12713, "LiveBloggerCount": 25225, "BloggerCount": 37404}, {"d": "04/07", "dt": "2026/04/07", "AwemeBloggerCount": 12667, "LiveBloggerCount": 28148, "BloggerCount": 40261}, {"d": "04/08", "dt": "2026/04/08", "AwemeBloggerCount": 13729, "LiveBloggerCount": 29262, "BloggerCount": 42346}, {"d": "04/09", "dt": "2026/04/09", "AwemeBloggerCount": 13500, "LiveBloggerCount": 29346, "BloggerCount": 42182}, {"d": "04/10", "dt": "2026/04/10", "AwemeBloggerCount": 13663, "LiveBloggerCount": 29453, "BloggerCount": 42471}, {"d": "04/11", "dt": "2026/04/11", "AwemeBloggerCount": 13259, "LiveBloggerCount": 28204, "BloggerCount": 40874}, {"d": "04/12", "dt": "2026/04/12", "AwemeBloggerCount": 12857, "LiveBloggerCount": 27338, "BloggerCount": 39660}, {"d": "04/13", "dt": "2026/04/13", "AwemeBloggerCount": 13737, "LiveBloggerCount": 28179, "BloggerCount": 41313}, {"d": "04/14", "dt": "2026/04/14", "AwemeBloggerCount": 13481, "LiveBloggerCount": 29750, "BloggerCount": 42551}, {"d": "04/15", "dt": "2026/04/15", "AwemeBloggerCount": 13670, "LiveBloggerCount": 29984, "BloggerCount": 43008}, {"d": "04/16", "dt": "2026/04/16", "AwemeBloggerCount": 14121, "LiveBloggerCount": 29247, "BloggerCount": 42688}, {"d": "04/17", "dt": "2026/04/17", "AwemeBloggerCount": 13936, "LiveBloggerCount": 29535, "BloggerCount": 42817}, {"d": "04/18", "dt": "2026/04/18", "AwemeBloggerCount": 13623, "LiveBloggerCount": 27417, "BloggerCount": 40425}, {"d": "04/19", "dt": "2026/04/19", "AwemeBloggerCount": 12400, "LiveBloggerCount": 26890, "BloggerCount": 38710}, {"d": "04/20", "dt": "2026/04/20", "AwemeBloggerCount": 14550, "LiveBloggerCount": 28163, "BloggerCount": 42050}, {"d": "04/21", "dt": "2026/04/21", "AwemeBloggerCount": 14640, "LiveBloggerCount": 29399, "BloggerCount": 43396}, {"d": "04/22", "dt": "2026/04/22", "AwemeBloggerCount": 14839, "LiveBloggerCount": 29935, "BloggerCount": 44090}, {"d": "04/23", "dt": "2026/04/23", "AwemeBloggerCount": 14967, "LiveBloggerCount": 30142, "BloggerCount": 44436}, {"d": "04/24", "dt": "2026/04/24", "AwemeBloggerCount": 14776, "LiveBloggerCount": 30897, "BloggerCount": 45017}, {"d": "04/25", "dt": "2026/04/25", "AwemeBloggerCount": 15223, "LiveBloggerCount": 29582, "BloggerCount": 44188}, {"d": "04/26", "dt": "2026/04/26", "AwemeBloggerCount": 14532, "LiveBloggerCount": 29106, "BloggerCount": 43050}, {"d": "04/27", "dt": "2026/04/27", "AwemeBloggerCount": 14978, "LiveBloggerCount": 30393, "BloggerCount": 44705}, {"d": "04/28", "dt": "2026/04/28", "AwemeBloggerCount": 15246, "LiveBloggerCount": 31298, "BloggerCount": 45853}, {"d": "04/29", "dt": "2026/04/29", "AwemeBloggerCount": 14896, "LiveBloggerCount": 31101, "BloggerCount": 45340}, {"d": "04/30", "dt": "2026/04/30", "AwemeBloggerCount": 14366, "LiveBloggerCount": 28813, "BloggerCount": 42541}, {"d": "05/01", "dt": "2026/05/01", "AwemeBloggerCount": 13254, "LiveBloggerCount": 24958, "BloggerCount": 37687}, {"d": "05/02", "dt": "2026/05/02", "AwemeBloggerCount": 13493, "LiveBloggerCount": 25184, "BloggerCount": 38157}, {"d": "05/03", "dt": "2026/05/03", "AwemeBloggerCount": 13517, "LiveBloggerCount": 26023, "BloggerCount": 38996}, {"d": "05/04", "dt": "2026/05/04", "AwemeBloggerCount": 14211, "LiveBloggerCount": 26583, "BloggerCount": 40234}, {"d": "05/05", "dt": "2026/05/05", "AwemeBloggerCount": 14513, "LiveBloggerCount": 28069, "BloggerCount": 41978}, {"d": "05/06", "dt": "2026/05/06", "AwemeBloggerCount": 14661, "LiveBloggerCount": 30288, "BloggerCount": 44304}, {"d": "05/07", "dt": "2026/05/07", "AwemeBloggerCount": 14928, "LiveBloggerCount": 31112, "BloggerCount": 45350}, {"d": "05/08", "dt": "2026/05/08", "AwemeBloggerCount": 14785, "LiveBloggerCount": 31720, "BloggerCount": 45800}, {"d": "05/09", "dt": "2026/05/09", "AwemeBloggerCount": 14838, "LiveBloggerCount": 30480, "BloggerCount": 44635}, {"d": "05/10", "dt": "2026/05/10", "AwemeBloggerCount": 14132, "LiveBloggerCount": 28580, "BloggerCount": 42112}, {"d": "05/11", "dt": "2026/05/11", "AwemeBloggerCount": 15725, "LiveBloggerCount": 30383, "BloggerCount": 45435}, {"d": "05/12", "dt": "2026/05/12", "AwemeBloggerCount": 15577, "LiveBloggerCount": 31362, "BloggerCount": 46267}, {"d": "05/13", "dt": "2026/05/13", "AwemeBloggerCount": 15419, "LiveBloggerCount": 31579, "BloggerCount": 46309}, {"d": "05/14", "dt": "2026/05/14", "AwemeBloggerCount": 15839, "LiveBloggerCount": 31858, "BloggerCount": 47004}, {"d": "05/15", "dt": "2026/05/15", "AwemeBloggerCount": 15412, "LiveBloggerCount": 32093, "BloggerCount": 46812}, {"d": "05/16", "dt": "2026/05/16", "AwemeBloggerCount": 15204, "LiveBloggerCount": 30128, "BloggerCount": 44664}, {"d": "05/17", "dt": "2026/05/17", "AwemeBloggerCount": 14916, "LiveBloggerCount": 29726, "BloggerCount": 43972}, {"d": "05/18", "dt": "2026/05/18", "AwemeBloggerCount": 16336, "LiveBloggerCount": 30519, "BloggerCount": 46154}, {"d": "05/19", "dt": "2026/05/19", "AwemeBloggerCount": 16022, "LiveBloggerCount": 32213, "BloggerCount": 47532}, {"d": "05/20", "dt": "2026/05/20", "AwemeBloggerCount": 15907, "LiveBloggerCount": 31976, "BloggerCount": 47163}, {"d": "05/21", "dt": "2026/05/21", "AwemeBloggerCount": 15966, "LiveBloggerCount": 30765, "BloggerCount": 45998}, {"d": "05/22", "dt": "2026/05/22", "AwemeBloggerCount": 15826, "LiveBloggerCount": 31939, "BloggerCount": 47054}, {"d": "05/23", "dt": "2026/05/23", "AwemeBloggerCount": 15009, "LiveBloggerCount": 30578, "BloggerCount": 44930}, {"d": "05/24", "dt": "2026/05/24", "AwemeBloggerCount": 14311, "LiveBloggerCount": 29044, "BloggerCount": 42726}, {"d": "05/25", "dt": "2026/05/25", "AwemeBloggerCount": 15580, "LiveBloggerCount": 30434, "BloggerCount": 45310}, {"d": "05/26", "dt": "2026/05/26", "AwemeBloggerCount": 15395, "LiveBloggerCount": 31700, "BloggerCount": 46363}, {"d": "05/27", "dt": "2026/05/27", "AwemeBloggerCount": 15664, "LiveBloggerCount": 32502, "BloggerCount": 47454}, {"d": "05/28", "dt": "2026/05/28", "AwemeBloggerCount": 15204, "LiveBloggerCount": 32547, "BloggerCount": 47066}, {"d": "05/29", "dt": "2026/05/29", "AwemeBloggerCount": 15706, "LiveBloggerCount": 32472, "BloggerCount": 47455}, {"d": "05/30", "dt": "2026/05/30", "AwemeBloggerCount": 15375, "LiveBloggerCount": 31314, "BloggerCount": 46051}, {"d": "05/31", "dt": "2026/05/31", "AwemeBloggerCount": 15032, "LiveBloggerCount": 30006, "BloggerCount": 44422}, {"d": "06/01", "dt": "2026/06/01", "AwemeBloggerCount": 15916, "LiveBloggerCount": 30170, "BloggerCount": 45451}, {"d": "06/02", "dt": "2026/06/02", "AwemeBloggerCount": 16231, "LiveBloggerCount": 32553, "BloggerCount": 48039}, {"d": "06/03", "dt": "2026/06/03", "AwemeBloggerCount": 16530, "LiveBloggerCount": 32881, "BloggerCount": 48658}, {"d": "06/04", "dt": "2026/06/04", "AwemeBloggerCount": 16618, "LiveBloggerCount": 33016, "BloggerCount": 48847}, {"d": "06/05", "dt": "2026/06/05", "AwemeBloggerCount": 16911, "LiveBloggerCount": 33080, "BloggerCount": 49248}, {"d": "06/06", "dt": "2026/06/06", "AwemeBloggerCount": 16931, "LiveBloggerCount": 32183, "BloggerCount": 48435}, {"d": "06/07", "dt": "2026/06/07", "AwemeBloggerCount": 16177, "LiveBloggerCount": 31126, "BloggerCount": 46620}, {"d": "06/08", "dt": "2026/06/08", "AwemeBloggerCount": 17280, "LiveBloggerCount": 32019, "BloggerCount": 48598}, {"d": "06/09", "dt": "2026/06/09", "AwemeBloggerCount": 17645, "LiveBloggerCount": 33737, "BloggerCount": 50631}, {"d": "06/10", "dt": "2026/06/10", "AwemeBloggerCount": 17491, "LiveBloggerCount": 34363, "BloggerCount": 51113}, {"d": "06/11", "dt": "2026/06/11", "AwemeBloggerCount": 17235, "LiveBloggerCount": 35484, "BloggerCount": 51967}, {"d": "06/12", "dt": "2026/06/12", "AwemeBloggerCount": 15747, "LiveBloggerCount": 35239, "BloggerCount": 50293}, {"d": "06/13", "dt": "2026/06/13", "AwemeBloggerCount": 16576, "LiveBloggerCount": 33865, "BloggerCount": 49726}, {"d": "06/14", "dt": "2026/06/14", "AwemeBloggerCount": 15871, "LiveBloggerCount": 32682, "BloggerCount": 47908}, {"d": "06/15", "dt": "2026/06/15", "AwemeBloggerCount": 16750, "LiveBloggerCount": 33781, "BloggerCount": 49809}, {"d": "06/16", "dt": "2026/06/16", "AwemeBloggerCount": 15966, "LiveBloggerCount": 35154, "BloggerCount": 50396}, {"d": "06/17", "dt": "2026/06/17", "AwemeBloggerCount": 15467, "LiveBloggerCount": 35346, "BloggerCount": 50101}, {"d": "06/18", "dt": "2026/06/18", "AwemeBloggerCount": 14522, "LiveBloggerCount": 33996, "BloggerCount": 47858}, {"d": "06/19", "dt": "2026/06/19", "AwemeBloggerCount": 13588, "LiveBloggerCount": 28304, "BloggerCount": 41357}, {"d": "06/20", "dt": "2026/06/20", "AwemeBloggerCount": 13720, "LiveBloggerCount": 30612, "BloggerCount": 43750}, {"d": "06/21", "dt": "2026/06/21", "AwemeBloggerCount": 14266, "LiveBloggerCount": 32031, "BloggerCount": 45685}, {"d": "06/22", "dt": "2026/06/22", "AwemeBloggerCount": 14583, "LiveBloggerCount": 33642, "BloggerCount": 47576}, {"d": "06/23", "dt": "2026/06/23", "AwemeBloggerCount": 9124, "LiveBloggerCount": 34178, "BloggerCount": 42810}]}, "商品分析-priceTrend": {"30d": [{"d": "05/25", "dt": "2026/05/25"}, {"d": "05/26", "dt": "2026/05/26"}, {"d": "05/27", "dt": "2026/05/27"}, {"d": "05/28", "dt": "2026/05/28"}, {"d": "05/29", "dt": "2026/05/29"}, {"d": "05/30", "dt": "2026/05/30"}, {"d": "05/31", "dt": "2026/05/31"}, {"d": "06/01", "dt": "2026/06/01"}, {"d": "06/02", "dt": "2026/06/02"}, {"d": "06/03", "dt": "2026/06/03"}, {"d": "06/04", "dt": "2026/06/04"}, {"d": "06/05", "dt": "2026/06/05"}, {"d": "06/06", "dt": "2026/06/06"}, {"d": "06/07", "dt": "2026/06/07"}, {"d": "06/08", "dt": "2026/06/08"}, {"d": "06/09", "dt": "2026/06/09"}, {"d": "06/10", "dt": "2026/06/10"}, {"d": "06/11", "dt": "2026/06/11"}, {"d": "06/12", "dt": "2026/06/12"}, {"d": "06/13", "dt": "2026/06/13"}, {"d": "06/14", "dt": "2026/06/14"}, {"d": "06/15", "dt": "2026/06/15"}, {"d": "06/16", "dt": "2026/06/16"}, {"d": "06/17", "dt": "2026/06/17"}, {"d": "06/18", "dt": "2026/06/18"}, {"d": "06/19", "dt": "2026/06/19"}, {"d": "06/20", "dt": "2026/06/20"}, {"d": "06/21", "dt": "2026/06/21"}, {"d": "06/22", "dt": "2026/06/22"}, {"d": "06/23", "dt": "2026/06/23"}], "90d": [{"d": "03/26", "dt": "2026/03/26"}, {"d": "03/27", "dt": "2026/03/27"}, {"d": "03/28", "dt": "2026/03/28"}, {"d": "03/29", "dt": "2026/03/29"}, {"d": "03/30", "dt": "2026/03/30"}, {"d": "03/31", "dt": "2026/03/31"}, {"d": "04/01", "dt": "2026/04/01"}, {"d": "04/02", "dt": "2026/04/02"}, {"d": "04/03", "dt": "2026/04/03"}, {"d": "04/04", "dt": "2026/04/04"}, {"d": "04/05", "dt": "2026/04/05"}, {"d": "04/06", "dt": "2026/04/06"}, {"d": "04/07", "dt": "2026/04/07"}, {"d": "04/08", "dt": "2026/04/08"}, {"d": "04/09", "dt": "2026/04/09"}, {"d": "04/10", "dt": "2026/04/10"}, {"d": "04/11", "dt": "2026/04/11"}, {"d": "04/12", "dt": "2026/04/12"}, {"d": "04/13", "dt": "2026/04/13"}, {"d": "04/14", "dt": "2026/04/14"}, {"d": "04/15", "dt": "2026/04/15"}, {"d": "04/16", "dt": "2026/04/16"}, {"d": "04/17", "dt": "2026/04/17"}, {"d": "04/18", "dt": "2026/04/18"}, {"d": "04/19", "dt": "2026/04/19"}, {"d": "04/20", "dt": "2026/04/20"}, {"d": "04/21", "dt": "2026/04/21"}, {"d": "04/22", "dt": "2026/04/22"}, {"d": "04/23", "dt": "2026/04/23"}, {"d": "04/24", "dt": "2026/04/24"}, {"d": "04/25", "dt": "2026/04/25"}, {"d": "04/26", "dt": "2026/04/26"}, {"d": "04/27", "dt": "2026/04/27"}, {"d": "04/28", "dt": "2026/04/28"}, {"d": "04/29", "dt": "2026/04/29"}, {"d": "04/30", "dt": "2026/04/30"}, {"d": "05/01", "dt": "2026/05/01"}, {"d": "05/02", "dt": "2026/05/02"}, {"d": "05/03", "dt": "2026/05/03"}, {"d": "05/04", "dt": "2026/05/04"}, {"d": "05/05", "dt": "2026/05/05"}, {"d": "05/06", "dt": "2026/05/06"}, {"d": "05/07", "dt": "2026/05/07"}, {"d": "05/08", "dt": "2026/05/08"}, {"d": "05/09", "dt": "2026/05/09"}, {"d": "05/10", "dt": "2026/05/10"}, {"d": "05/11", "dt": "2026/05/11"}, {"d": "05/12", "dt": "2026/05/12"}, {"d": "05/13", "dt": "2026/05/13"}, {"d": "05/14", "dt": "2026/05/14"}, {"d": "05/15", "dt": "2026/05/15"}, {"d": "05/16", "dt": "2026/05/16"}, {"d": "05/17", "dt": "2026/05/17"}, {"d": "05/18", "dt": "2026/05/18"}, {"d": "05/19", "dt": "2026/05/19"}, {"d": "05/20", "dt": "2026/05/20"}, {"d": "05/21", "dt": "2026/05/21"}, {"d": "05/22", "dt": "2026/05/22"}, {"d": "05/23", "dt": "2026/05/23"}, {"d": "05/24", "dt": "2026/05/24"}, {"d": "05/25", "dt": "2026/05/25"}, {"d": "05/26", "dt": "2026/05/26"}, {"d": "05/27", "dt": "2026/05/27"}, {"d": "05/28", "dt": "2026/05/28"}, {"d": "05/29", "dt": "2026/05/29"}, {"d": "05/30", "dt": "2026/05/30"}, {"d": "05/31", "dt": "2026/05/31"}, {"d": "06/01", "dt": "2026/06/01"}, {"d": "06/02", "dt": "2026/06/02"}, {"d": "06/03", "dt": "2026/06/03"}, {"d": "06/04", "dt": "2026/06/04"}, {"d": "06/05", "dt": "2026/06/05"}, {"d": "06/06", "dt": "2026/06/06"}, {"d": "06/07", "dt": "2026/06/07"}, {"d": "06/08", "dt": "2026/06/08"}, {"d": "06/09", "dt": "2026/06/09"}, {"d": "06/10", "dt": "2026/06/10"}, {"d": "06/11", "dt": "2026/06/11"}, {"d": "06/12", "dt": "2026/06/12"}, {"d": "06/13", "dt": "2026/06/13"}, {"d": "06/14", "dt": "2026/06/14"}, {"d": "06/15", "dt": "2026/06/15"}, {"d": "06/16", "dt": "2026/06/16"}, {"d": "06/17", "dt": "2026/06/17"}, {"d": "06/18", "dt": "2026/06/18"}, {"d": "06/19", "dt": "2026/06/19"}, {"d": "06/20", "dt": "2026/06/20"}, {"d": "06/21", "dt": "2026/06/21"}, {"d": "06/22", "dt": "2026/06/22"}, {"d": "06/23", "dt": "2026/06/23"}]}}